Workbook
Name SegmentaciónDeDatos_C_Edad: #N/A
Name SegmentaciónDeDatos_Clase: #N/A
Name SegmentaciónDeDatos_Sexo: #N/A

Sheet Tipos de análisis
B3: Análisis en Grupos de Datos | E3: Todo es una categoría y se observa un valor resumido
F4: Valor agregado: Suma, Promedio, Recuento, Mínimo, Máximo, …
C6: Conteos de grupos que se transforman en probabilidades
B9: Análisis de Tendencia de Datos | E9: Todo es una tendencia y ser observa un valor continuo
F10: Series de datos: Lineales/Indexados, Temporales/Periódicos
C12: Acumulaciones, Diferencias y Regresiones que se transforman en tendencias

Sheet Titanic
G2: {=SUM((Titanic[Edad]="")*1)} -> 177
B5: Indice | C5: Sobrevive | D5: Clase | E5: Nombre | F5: Sexo | G5: Edad | H5: Familia Horizontal | I5: Familia Vertical | J5: Pagado | K5: Cabina | L5: Puerto | M5: C Sobrevive | N5: C Clase | O5: C Sexo | P5: Edad Corrigida | Q5: C Edad | R5: Familiares | S5: C Familiares | T5: C Pago | U5: C Cabina | V5: C Puerto
B6: 1 | C6: 0 | D6: 3 | E6: Braund, Mr. Owen Harris | F6: Hombre | G6: 22 | H6: 1 | I6: 0 | J6: 725 | K6: 0 | L6: Southampton | M6: =IF(Titanic[[#This Row],[Sobrevive]]=1, "SOBREVIVE", "NO SOBREVIVE") -> NO SOBREVIVE | N6: =LOOKUP(Titanic[[#This Row],[Clase]],{1,2,3}, {"PRIMERA","SEGUNDA","TERCERA"}) -> TERCERA | O6: =IF(Titanic[[#This Row],[Sexo]]="Hombre", "HOMBRE", "MUJER") -> HOMBRE | P6: =IF(Titanic[[#This Row],[Edad]]="", "", IF(Titanic[[#This Row],[Edad]]>=100, Titanic[[#This Row],[Edad]] / 10, Titanic[[#This Row],[Edad]])) -> 22 | Q6: =IFERROR(LOOKUP(Titanic[[#This Row],[Edad Corrigida]],'Práctica 1'!$K$231:$K$240,'Práctica 1'!$L$231:$L$240), "DESCONOCIDO") -> 3. JOVEN | R6: =Titanic[[#This Row],[Familia Horizontal]]+Titanic[[#This Row],[Familia Vertical]] -> 1
B7: 2 | C7: 1 | D7: 1 | E7: Cumings, Mrs. John Bradley (Florence Briggs Thayer) | F7: Mujer | G7: 38 | H7: 1 | I7: 0 | J7: 712833 | K7: 1 | L7: Cherburg | M7: =IF(Titanic[[#This Row],[Sobrevive]]=1, "SOBREVIVE", "NO SOBREVIVE") -> SOBREVIVE | N7: =LOOKUP(Titanic[[#This Row],[Clase]],{1,2,3}, {"PRIMERA","SEGUNDA","TERCERA"}) -> PRIMERA | O7: =IF(Titanic[[#This Row],[Sexo]]="Hombre", "HOMBRE", "MUJER") -> MUJER | P7: =IF(Titanic[[#This Row],[Edad]]="", "", IF(Titanic[[#This Row],[Edad]]>=100, Titanic[[#This Row],[Edad]] / 10, Titanic[[#This Row],[Edad]])) -> 38 | Q7: =IFERROR(LOOKUP(Titanic[[#This Row],[Edad Corrigida]],'Práctica 1'!$K$231:$K$240,'Práctica 1'!$L$231:$L$240), "DESCONOCIDO") -> 7. ADULTO 2 | R7: =Titanic[[#This Row],[Familia Horizontal]]+Titanic[[#This Row],[Familia Vertical]] -> 1
B8: 3 | C8: 1 | D8: 3 | E8: Heikkinen, Miss. Laina | F8: Mujer | G8: 26 | H8: 0 | I8: 0 | J8: 7925 | K8: 0 | L8: Southampton | M8: =IF(Titanic[[#This Row],[Sobrevive]]=1, "SOBREVIVE", "NO SOBREVIVE") -> SOBREVIVE | N8: =LOOKUP(Titanic[[#This Row],[Clase]],{1,2,3}, {"PRIMERA","SEGUNDA","TERCERA"}) -> TERCERA | O8: =IF(Titanic[[#This Row],[Sexo]]="Hombre", "HOMBRE", "MUJER") -> MUJER | P8: =IF(Titanic[[#This Row],[Edad]]="", "", IF(Titanic[[#This Row],[Edad]]>=100, Titanic[[#This Row],[Edad]] / 10, Titanic[[#This Row],[Edad]])) -> 26 | Q8: =IFERROR(LOOKUP(Titanic[[#This Row],[Edad Corrigida]],'Práctica 1'!$K$231:$K$240,'Práctica 1'!$L$231:$L$240), "DESCONOCIDO") -> 4. ADULTO JOVEN | R8: =Titanic[[#This Row],[Familia Horizontal]]+Titanic[[#This Row],[Familia Vertical]] -> 0
B9: 4 | C9: 1 | D9: 1 | E9: Futrelle, Mrs. Jacques Heath (Lily May Peel) | F9: Mujer | G9: 35 | H9: 1 | I9: 0 | J9: 531 | K9: 1 | L9: Southampton | M9: =IF(Titanic[[#This Row],[Sobrevive]]=1, "SOBREVIVE", "NO SOBREVIVE") -> SOBREVIVE | N9: =LOOKUP(Titanic[[#This Row],[Clase]],{1,2,3}, {"PRIMERA","SEGUNDA","TERCERA"}) -> PRIMERA | O9: =IF(Titanic[[#This Row],[Sexo]]="Hombre", "HOMBRE", "MUJER") -> MUJER | P9: =IF(Titanic[[#This Row],[Edad]]="", "", IF(Titanic[[#This Row],[Edad]]>=100, Titanic[[#This Row],[Edad]] / 10, Titanic[[#This Row],[Edad]])) -> 35 | Q9: =IFERROR(LOOKUP(Titanic[[#This Row],[Edad Corrigida]],'Práctica 1'!$K$231:$K$240,'Práctica 1'!$L$231:$L$240), "DESCONOCIDO") -> 6. ADULTO 1 | R9: =Titanic[[#This Row],[Familia Horizontal]]+Titanic[[#This Row],[Familia Vertical]] -> 1
B10: 5 | C10: 0 | D10: 3 | E10: Allen, Mr. William Henry | F10: Hombre | G10: 35 | H10: 0 | I10: 0 | J10: 805 | K10: 0 | L10: Southampton | M10: =IF(Titanic[[#This Row],[Sobrevive]]=1, "SOBREVIVE", "NO SOBREVIVE") -> NO SOBREVIVE | N10: =LOOKUP(Titanic[[#This Row],[Clase]],{1,2,3}, {"PRIMERA","SEGUNDA","TERCERA"}) -> TERCERA | O10: =IF(Titanic[[#This Row],[Sexo]]="Hombre", "HOMBRE", "MUJER") -> HOMBRE | P10: =IF(Titanic[[#This Row],[Edad]]="", "", IF(Titanic[[#This Row],[Edad]]>=100, Titanic[[#This Row],[Edad]] / 10, Titanic[[#This Row],[Edad]])) -> 35 | Q10: =IFERROR(LOOKUP(Titanic[[#This Row],[Edad Corrigida]],'Práctica 1'!$K$231:$K$240,'Práctica 1'!$L$231:$L$240), "DESCONOCIDO") -> 6. ADULTO 1 | R10: =Titanic[[#This Row],[Familia Horizontal]]+Titanic[[#This Row],[Familia Vertical]] -> 0
B11: 6 | C11: 0 | D11: 3 | E11: Moran, Mr. James | F11: Hombre | H11: 0 | I11: 0 | J11: 84583 | K11: 0 | L11: Queenstown | M11: =IF(Titanic[[#This Row],[Sobrevive]]=1, "SOBREVIVE", "NO SOBREVIVE") -> NO SOBREVIVE | N11: =LOOKUP(Titanic[[#This Row],[Clase]],{1,2,3}, {"PRIMERA","SEGUNDA","TERCERA"}) -> TERCERA | O11: =IF(Titanic[[#This Row],[Sexo]]="Hombre", "HOMBRE", "MUJER") -> HOMBRE | P11: =IF(Titanic[[#This Row],[Edad]]="", "", IF(Titanic[[#This Row],[Edad]]>=100, Titanic[[#This Row],[Edad]] / 10, Titanic[[#This Row],[Edad]])) | Q11: =IFERROR(LOOKUP(Titanic[[#This Row],[Edad Corrigida]],'Práctica 1'!$K$231:$K$240,'Práctica 1'!$L$231:$L$240), "DESCONOCIDO") -> DESCONOCIDO | R11: =Titanic[[#This Row],[Familia Horizontal]]+Titanic[[#This Row],[Familia Vertical]] -> 0
B12: 7 | C12: 0 | D12: 1 | E12: McCarthy, Mr. Timothy J | F12: Hombre | G12: 54 | H12: 0 | I12: 0 | J12: 518625 | K12: 1 | L12: Southampton | M12: =IF(Titanic[[#This Row],[Sobrevive]]=1, "SOBREVIVE", "NO SOBREVIVE") -> NO SOBREVIVE | N12: =LOOKUP(Titanic[[#This Row],[Clase]],{1,2,3}, {"PRIMERA","SEGUNDA","TERCERA"}) -> PRIMERA | O12: =IF(Titanic[[#This Row],[Sexo]]="Hombre", "HOMBRE", "MUJER") -> HOMBRE | P12: =IF(Titanic[[#This Row],[Edad]]="", "", IF(Titanic[[#This Row],[Edad]]>=100, Titanic[[#This Row],[Edad]] / 10, Titanic[[#This Row],[Edad]])) -> 54 | Q12: =IFERROR(LOOKUP(Titanic[[#This Row],[Edad Corrigida]],'Práctica 1'!$K$231:$K$240,'Práctica 1'!$L$231:$L$240), "DESCONOCIDO") -> 9. ADULTO 4 | R12: =Titanic[[#This Row],[Familia Horizontal]]+Titanic[[#This Row],[Familia Vertical]] -> 0
B13: 8 | C13: 0 | D13: 3 | E13: Palsson, Master. Gosta Leonard | F13: Hombre | G13: 2 | H13: 3 | I13: 1 | J13: 21075 | K13: 0 | L13: Southampton | M13: =IF(Titanic[[#This Row],[Sobrevive]]=1, "SOBREVIVE", "NO SOBREVIVE") -> NO SOBREVIVE | N13: =LOOKUP(Titanic[[#This Row],[Clase]],{1,2,3}, {"PRIMERA","SEGUNDA","TERCERA"}) -> TERCERA | O13: =IF(Titanic[[#This Row],[Sexo]]="Hombre", "HOMBRE", "MUJER") -> HOMBRE | P13: =IF(Titanic[[#This Row],[Edad]]="", "", IF(Titanic[[#This Row],[Edad]]>=100, Titanic[[#This Row],[Edad]] / 10, Titanic[[#This Row],[Edad]])) -> 2 | Q13: =IFERROR(LOOKUP(Titanic[[#This Row],[Edad Corrigida]],'Práctica 1'!$K$231:$K$240,'Práctica 1'!$L$231:$L$240), "DESCONOCIDO") -> DESCONOCIDO | R13: =Titanic[[#This Row],[Familia Horizontal]]+Titanic[[#This Row],[Familia Vertical]] -> 4
B14: 9 | C14: 1 | D14: 3 | E14: Johnson, Mrs. Oscar W (Elisabeth Vilhelmina Berg) | F14: Mujer | G14: 27 | H14: 0 | I14: 2 | J14: 111333 | K14: 0 | L14: Southampton | M14: =IF(Titanic[[#This Row],[Sobrevive]]=1, "SOBREVIVE", "NO SOBREVIVE") -> SOBREVIVE | N14: =LOOKUP(Titanic[[#This Row],[Clase]],{1,2,3}, {"PRIMERA","SEGUNDA","TERCERA"}) -> TERCERA | O14: =IF(Titanic[[#This Row],[Sexo]]="Hombre", "HOMBRE", "MUJER") -> MUJER | P14: =IF(Titanic[[#This Row],[Edad]]="", "", IF(Titanic[[#This Row],[Edad]]>=100, Titanic[[#This Row],[Edad]] / 10, Titanic[[#This Row],[Edad]])) -> 27 | Q14: =IFERROR(LOOKUP(Titanic[[#This Row],[Edad Corrigida]],'Práctica 1'!$K$231:$K$240,'Práctica 1'!$L$231:$L$240), "DESCONOCIDO") -> 4. ADULTO JOVEN | R14: =Titanic[[#This Row],[Familia Horizontal]]+Titanic[[#This Row],[Familia Vertical]] -> 2
B15: 10 | C15: 1 | D15: 2 | E15: Nasser, Mrs. Nicholas (Adele Achem) | F15: Mujer | G15: 14 | H15: 1 | I15: 0 | J15: 300708 | K15: 0 | L15: Cherburg | M15: =IF(Titanic[[#This Row],[Sobrevive]]=1, "SOBREVIVE", "NO SOBREVIVE") -> SOBREVIVE | N15: =LOOKUP(Titanic[[#This Row],[Clase]],{1,2,3}, {"PRIMERA","SEGUNDA","TERCERA"}) -> SEGUNDA | O15: =IF(Titanic[[#This Row],[Sexo]]="Hombre", "HOMBRE", "MUJER") -> MUJER | P15: =IF(Titanic[[#This Row],[Edad]]="", "", IF(Titanic[[#This Row],[Edad]]>=100, Titanic[[#This Row],[Edad]] / 10, Titanic[[#This Row],[Edad]])) -> 14 | Q15: =IFERROR(LOOKUP(Titanic[[#This Row],[Edad Corrigida]],'Práctica 1'!$K$231:$K$240,'Práctica 1'!$L$231:$L$240), "DESCONOCIDO") -> DESCONOCIDO | R15: =Titanic[[#This Row],[Familia Horizontal]]+Titanic[[#This Row],[Familia Vertical]] -> 1
B16: 11 | C16: 1 | D16: 3 | E16: Sandstrom, Miss. Marguerite Rut | F16: Mujer | G16: 4 | H16: 1 | I16: 1 | J16: 167 | K16: 1 | L16: Southampton | M16: =IF(Titanic[[#This Row],[Sobrevive]]=1, "SOBREVIVE", "NO SOBREVIVE") -> SOBREVIVE | N16: =LOOKUP(Titanic[[#This Row],[Clase]],{1,2,3}, {"PRIMERA","SEGUNDA","TERCERA"}) -> TERCERA | O16: =IF(Titanic[[#This Row],[Sexo]]="Hombre", "HOMBRE", "MUJER") -> MUJER | P16: =IF(Titanic[[#This Row],[Edad]]="", "", IF(Titanic[[#This Row],[Edad]]>=100, Titanic[[#This Row],[Edad]] / 10, Titanic[[#This Row],[Edad]])) -> 4 | Q16: =IFERROR(LOOKUP(Titanic[[#This Row],[Edad Corrigida]],'Práctica 1'!$K$231:$K$240,'Práctica 1'!$L$231:$L$240), "DESCONOCIDO") -> DESCONOCIDO | R16: =Titanic[[#This Row],[Familia Horizontal]]+Titanic[[#This Row],[Familia Vertical]] -> 2
B17: 12 | C17: 1 | D17: 1 | E17: Bonnell, Miss. Elizabeth | F17: Mujer | G17: 58 | H17: 0 | I17: 0 | J17: 2655 | K17: 1 | L17: Southampton | M17: =IF(Titanic[[#This Row],[Sobrevive]]=1, "SOBREVIVE", "NO SOBREVIVE") -> SOBREVIVE | N17: =LOOKUP(Titanic[[#This Row],[Clase]],{1,2,3}, {"PRIMERA","SEGUNDA","TERCERA"}) -> PRIMERA | O17: =IF(Titanic[[#This Row],[Sexo]]="Hombre", "HOMBRE", "MUJER") -> MUJER | P17: =IF(Titanic[[#This Row],[Edad]]="", "", IF(Titanic[[#This Row],[Edad]]>=100, Titanic[[#This Row],[Edad]] / 10, Titanic[[#This Row],[Edad]])) -> 58 | Q17: =IFERROR(LOOKUP(Titanic[[#This Row],[Edad Corrigida]],'Práctica 1'!$K$231:$K$240,'Práctica 1'!$L$231:$L$240), "DESCONOCIDO") -> 9. ADULTO 4 | R17: =Titanic[[#This Row],[Familia Horizontal]]+Titanic[[#This Row],[Familia Vertical]] -> 0
B18: 13 | C18: 0 | D18: 3 | E18: Saundercock, Mr. William Henry | F18: Hombre | G18: 20 | H18: 0 | I18: 0 | J18: 805 | K18: 0 | L18: Southampton | M18: =IF(Titanic[[#This Row],[Sobrevive]]=1, "SOBREVIVE", "NO SOBREVIVE") -> NO SOBREVIVE | N18: =LOOKUP(Titanic[[#This Row],[Clase]],{1,2,3}, {"PRIMERA","SEGUNDA","TERCERA"}) -> TERCERA | O18: =IF(Titanic[[#This Row],[Sexo]]="Hombre", "HOMBRE", "MUJER") -> HOMBRE | P18: =IF(Titanic[[#This Row],[Edad]]="", "", IF(Titanic[[#This Row],[Edad]]>=100, Titanic[[#This Row],[Edad]] / 10, Titanic[[#This Row],[Edad]])) -> 20 | Q18: =IFERROR(LOOKUP(Titanic[[#This Row],[Edad Corrigida]],'Práctica 1'!$K$231:$K$240,'Práctica 1'!$L$231:$L$240), "DESCONOCIDO") -> 2. ADOLESCENTE | R18: =Titanic[[#This Row],[Familia Horizontal]]+Titanic[[#This Row],[Familia Vertical]] -> 0
B19: 14 | C19: 0 | D19: 3 | E19: Andersson, Mr. Anders Johan | F19: Hombre | G19: 39 | H19: 1 | I19: 5 | J19: 31275 | K19: 0 | L19: Southampton | M19: =IF(Titanic[[#This Row],[Sobrevive]]=1, "SOBREVIVE", "NO SOBREVIVE") -> NO SOBREVIVE | N19: =LOOKUP(Titanic[[#This Row],[Clase]],{1,2,3}, {"PRIMERA","SEGUNDA","TERCERA"}) -> TERCERA | O19: =IF(Titanic[[#This Row],[Sexo]]="Hombre", "HOMBRE", "MUJER") -> HOMBRE | P19: =IF(Titanic[[#This Row],[Edad]]="", "", IF(Titanic[[#This Row],[Edad]]>=100, Titanic[[#This Row],[Edad]] / 10, Titanic[[#This Row],[Edad]])) -> 39 | Q19: =IFERROR(LOOKUP(Titanic[[#This Row],[Edad Corrigida]],'Práctica 1'!$K$231:$K$240,'Práctica 1'!$L$231:$L$240), "DESCONOCIDO") -> 7. ADULTO 2 | R19: =Titanic[[#This Row],[Familia Horizontal]]+Titanic[[#This Row],[Familia Vertical]] -> 6
B20: 15 | C20: 0 | D20: 3 | E20: Vestrom, Miss. Hulda Amanda Adolfina | F20: Mujer | G20: 14 | H20: 0 | I20: 0 | J20: 78542 | K20: 0 | L20: Southampton | M20: =IF(Titanic[[#This Row],[Sobrevive]]=1, "SOBREVIVE", "NO SOBREVIVE") -> NO SOBREVIVE | N20: =LOOKUP(Titanic[[#This Row],[Clase]],{1,2,3}, {"PRIMERA","SEGUNDA","TERCERA"}) -> TERCERA | O20: =IF(Titanic[[#This Row],[Sexo]]="Hombre", "HOMBRE", "MUJER") -> MUJER | P20: =IF(Titanic[[#This Row],[Edad]]="", "", IF(Titanic[[#This Row],[Edad]]>=100, Titanic[[#This Row],[Edad]] / 10, Titanic[[#This Row],[Edad]])) -> 14 | Q20: =IFERROR(LOOKUP(Titanic[[#This Row],[Edad Corrigida]],'Práctica 1'!$K$231:$K$240,'Práctica 1'!$L$231:$L$240), "DESCONOCIDO") -> DESCONOCIDO | R20: =Titanic[[#This Row],[Familia Horizontal]]+Titanic[[#This Row],[Familia Vertical]] -> 0
B21: 16 | C21: 1 | D21: 2 | E21: Hewlett, Mrs. (Mary D Kingcome) | F21: Mujer | G21: 55 | H21: 0 | I21: 0 | J21: 16 | K21: 0 | L21: Southampton | M21: =IF(Titanic[[#This Row],[Sobrevive]]=1, "SOBREVIVE", "NO SOBREVIVE") -> SOBREVIVE | N21: =LOOKUP(Titanic[[#This Row],[Clase]],{1,2,3}, {"PRIMERA","SEGUNDA","TERCERA"}) -> SEGUNDA | O21: =IF(Titanic[[#This Row],[Sexo]]="Hombre", "HOMBRE", "MUJER") -> MUJER | P21: =IF(Titanic[[#This Row],[Edad]]="", "", IF(Titanic[[#This Row],[Edad]]>=100, Titanic[[#This Row],[Edad]] / 10, Titanic[[#This Row],[Edad]])) -> 55 | Q21: =IFERROR(LOOKUP(Titanic[[#This Row],[Edad Corrigida]],'Práctica 1'!$K$231:$K$240,'Práctica 1'!$L$231:$L$240), "DESCONOCIDO") -> 9. ADULTO 4 | R21: =Titanic[[#This Row],[Familia Horizontal]]+Titanic[[#This Row],[Familia Vertical]] -> 0
B22: 17 | C22: 0 | D22: 3 | E22: Rice, Master. Eugene | F22: Hombre | G22: 2 | H22: 4 | I22: 1 | J22: 29125 | K22: 0 | L22: Queenstown | M22: =IF(Titanic[[#This Row],[Sobrevive]]=1, "SOBREVIVE", "NO SOBREVIVE") -> NO SOBREVIVE | N22: =LOOKUP(Titanic[[#This Row],[Clase]],{1,2,3}, {"PRIMERA","SEGUNDA","TERCERA"}) -> TERCERA | O22: =IF(Titanic[[#This Row],[Sexo]]="Hombre", "HOMBRE", "MUJER") -> HOMBRE | P22: =IF(Titanic[[#This Row],[Edad]]="", "", IF(Titanic[[#This Row],[Edad]]>=100, Titanic[[#This Row],[Edad]] / 10, Titanic[[#This Row],[Edad]])) -> 2 | Q22: =IFERROR(LOOKUP(Titanic[[#This Row],[Edad Corrigida]],'Práctica 1'!$K$231:$K$240,'Práctica 1'!$L$231:$L$240), "DESCONOCIDO") -> DESCONOCIDO | R22: =Titanic[[#This Row],[Familia Horizontal]]+Titanic[[#This Row],[Familia Vertical]] -> 5
B23: 18 | C23: 1 | D23: 2 | E23: Williams, Mr. Charles Eugene | F23: Hombre | H23: 0 | I23: 0 | J23: 13 | K23: 0 | L23: Southampton | M23: =IF(Titanic[[#This Row],[Sobrevive]]=1, "SOBREVIVE", "NO SOBREVIVE") -> SOBREVIVE | N23: =LOOKUP(Titanic[[#This Row],[Clase]],{1,2,3}, {"PRIMERA","SEGUNDA","TERCERA"}) -> SEGUNDA | O23: =IF(Titanic[[#This Row],[Sexo]]="Hombre", "HOMBRE", "MUJER") -> HOMBRE | P23: =IF(Titanic[[#This Row],[Edad]]="", "", IF(Titanic[[#This Row],[Edad]]>=100, Titanic[[#This Row],[Edad]] / 10, Titanic[[#This Row],[Edad]])) | Q23: =IFERROR(LOOKUP(Titanic[[#This Row],[Edad Corrigida]],'Práctica 1'!$K$231:$K$240,'Práctica 1'!$L$231:$L$240), "DESCONOCIDO") -> DESCONOCIDO | R23: =Titanic[[#This Row],[Familia Horizontal]]+Titanic[[#This Row],[Familia Vertical]] -> 0
B24: 19 | C24: 0 | D24: 3 | E24: Vander Planke, Mrs. Julius (Emelia Maria Vandemoortele) | F24: Mujer | G24: 31 | H24: 1 | I24: 0 | J24: 18 | K24: 0 | L24: Southampton | M24: =IF(Titanic[[#This Row],[Sobrevive]]=1, "SOBREVIVE", "NO SOBREVIVE") -> NO SOBREVIVE | N24: =LOOKUP(Titanic[[#This Row],[Clase]],{1,2,3}, {"PRIMERA","SEGUNDA","TERCERA"}) -> TERCERA | O24: =IF(Titanic[[#This Row],[Sexo]]="Hombre", "HOMBRE", "MUJER") -> MUJER | P24: =IF(Titanic[[#This Row],[Edad]]="", "", IF(Titanic[[#This Row],[Edad]]>=100, Titanic[[#This Row],[Edad]] / 10, Titanic[[#This Row],[Edad]])) -> 31 | Q24: =IFERROR(LOOKUP(Titanic[[#This Row],[Edad Corrigida]],'Práctica 1'!$K$231:$K$240,'Práctica 1'!$L$231:$L$240), "DESCONOCIDO") -> 5. ADULTO | R24: =Titanic[[#This Row],[Familia Horizontal]]+Titanic[[#This Row],[Familia Vertical]] -> 1
B25: 20 | C25: 1 | D25: 3 | E25: Masselmani, Mrs. Fatima | F25: Mujer | H25: 0 | I25: 0 | J25: 7225 | K25: 0 | L25: Cherburg | M25: =IF(Titanic[[#This Row],[Sobrevive]]=1, "SOBREVIVE", "NO SOBREVIVE") -> SOBREVIVE | N25: =LOOKUP(Titanic[[#This Row],[Clase]],{1,2,3}, {"PRIMERA","SEGUNDA","TERCERA"}) -> TERCERA | O25: =IF(Titanic[[#This Row],[Sexo]]="Hombre", "HOMBRE", "MUJER") -> MUJER | P25: =IF(Titanic[[#This Row],[Edad]]="", "", IF(Titanic[[#This Row],[Edad]]>=100, Titanic[[#This Row],[Edad]] / 10, Titanic[[#This Row],[Edad]])) | Q25: =IFERROR(LOOKUP(Titanic[[#This Row],[Edad Corrigida]],'Práctica 1'!$K$231:$K$240,'Práctica 1'!$L$231:$L$240), "DESCONOCIDO") -> DESCONOCIDO | R25: =Titanic[[#This Row],[Familia Horizontal]]+Titanic[[#This Row],[Familia Vertical]] -> 0
B26: 21 | C26: 0 | D26: 2 | E26: Fynney, Mr. Joseph J | F26: Hombre | G26: 35 | H26: 0 | I26: 0 | J26: 26 | K26: 0 | L26: Southampton | M26: =IF(Titanic[[#This Row],[Sobrevive]]=1, "SOBREVIVE", "NO SOBREVIVE") -> NO SOBREVIVE | N26: =LOOKUP(Titanic[[#This Row],[Clase]],{1,2,3}, {"PRIMERA","SEGUNDA","TERCERA"}) -> SEGUNDA | O26: =IF(Titanic[[#This Row],[Sexo]]="Hombre", "HOMBRE", "MUJER") -> HOMBRE | P26: =IF(Titanic[[#This Row],[Edad]]="", "", IF(Titanic[[#This Row],[Edad]]>=100, Titanic[[#This Row],[Edad]] / 10, Titanic[[#This Row],[Edad]])) -> 35 | Q26: =IFERROR(LOOKUP(Titanic[[#This Row],[Edad Corrigida]],'Práctica 1'!$K$231:$K$240,'Práctica 1'!$L$231:$L$240), "DESCONOCIDO") -> 6. ADULTO 1 | R26: =Titanic[[#This Row],[Familia Horizontal]]+Titanic[[#This Row],[Familia Vertical]] -> 0
B27: 22 | C27: 1 | D27: 2 | E27: Beesley, Mr. Lawrence | F27: Hombre | G27: 34 | H27: 0 | I27: 0 | J27: 13 | K27: 1 | L27: Southampton | M27: =IF(Titanic[[#This Row],[Sobrevive]]=1, "SOBREVIVE", "NO SOBREVIVE") -> SOBREVIVE | N27: =LOOKUP(Titanic[[#This Row],[Clase]],{1,2,3}, {"PRIMERA","SEGUNDA","TERCERA"}) -> SEGUNDA | O27: =IF(Titanic[[#This Row],[Sexo]]="Hombre", "HOMBRE", "MUJER") -> HOMBRE | P27: =IF(Titanic[[#This Row],[Edad]]="", "", IF(Titanic[[#This Row],[Edad]]>=100, Titanic[[#This Row],[Edad]] / 10, Titanic[[#This Row],[Edad]])) -> 34 | Q27: =IFERROR(LOOKUP(Titanic[[#This Row],[Edad Corrigida]],'Práctica 1'!$K$231:$K$240,'Práctica 1'!$L$231:$L$240), "DESCONOCIDO") -> 6. ADULTO 1 | R27: =Titanic[[#This Row],[Familia Horizontal]]+Titanic[[#This Row],[Familia Vertical]] -> 0
B28: 23 | C28: 1 | D28: 3 | E28: McGowan, Miss. Anna "Annie" | F28: Mujer | G28: 15 | H28: 0 | I28: 0 | J28: 80292 | K28: 0 | L28: Queenstown | M28: =IF(Titanic[[#This Row],[Sobrevive]]=1, "SOBREVIVE", "NO SOBREVIVE") -> SOBREVIVE | N28: =LOOKUP(Titanic[[#This Row],[Clase]],{1,2,3}, {"PRIMERA","SEGUNDA","TERCERA"}) -> TERCERA | O28: =IF(Titanic[[#This Row],[Sexo]]="Hombre", "HOMBRE", "MUJER") -> MUJER | P28: =IF(Titanic[[#This Row],[Edad]]="", "", IF(Titanic[[#This Row],[Edad]]>=100, Titanic[[#This Row],[Edad]] / 10, Titanic[[#This Row],[Edad]])) -> 15 | Q28: =IFERROR(LOOKUP(Titanic[[#This Row],[Edad Corrigida]],'Práctica 1'!$K$231:$K$240,'Práctica 1'!$L$231:$L$240), "DESCONOCIDO") -> 1. INFANTE | R28: =Titanic[[#This Row],[Familia Horizontal]]+Titanic[[#This Row],[Familia Vertical]] -> 0
B29: 24 | C29: 1 | D29: 1 | E29: Sloper, Mr. William Thompson | F29: Hombre | G29: 28 | H29: 0 | I29: 0 | J29: 355 | K29: 1 | L29: Southampton | M29: =IF(Titanic[[#This Row],[Sobrevive]]=1, "SOBREVIVE", "NO SOBREVIVE") -> SOBREVIVE | N29: =LOOKUP(Titanic[[#This Row],[Clase]],{1,2,3}, {"PRIMERA","SEGUNDA","TERCERA"}) -> PRIMERA | O29: =IF(Titanic[[#This Row],[Sexo]]="Hombre", "HOMBRE", "MUJER") -> HOMBRE | P29: =IF(Titanic[[#This Row],[Edad]]="", "", IF(Titanic[[#This Row],[Edad]]>=100, Titanic[[#This Row],[Edad]] / 10, Titanic[[#This Row],[Edad]])) -> 28 | Q29: =IFERROR(LOOKUP(Titanic[[#This Row],[Edad Corrigida]],'Práctica 1'!$K$231:$K$240,'Práctica 1'!$L$231:$L$240), "DESCONOCIDO") -> 4. ADULTO JOVEN | R29: =Titanic[[#This Row],[Familia Horizontal]]+Titanic[[#This Row],[Familia Vertical]] -> 0
B30: 25 | C30: 0 | D30: 3 | E30: Palsson, Miss. Torborg Danira | F30: Mujer | G30: 8 | H30: 3 | I30: 1 | J30: 21075 | K30: 0 | L30: Southampton | M30: =IF(Titanic[[#This Row],[Sobrevive]]=1, "SOBREVIVE", "NO SOBREVIVE") -> NO SOBREVIVE | N30: =LOOKUP(Titanic[[#This Row],[Clase]],{1,2,3}, {"PRIMERA","SEGUNDA","TERCERA"}) -> TERCERA | O30: =IF(Titanic[[#This Row],[Sexo]]="Hombre", "HOMBRE", "MUJER") -> MUJER | P30: =IF(Titanic[[#This Row],[Edad]]="", "", IF(Titanic[[#This Row],[Edad]]>=100, Titanic[[#This Row],[Edad]] / 10, Titanic[[#This Row],[Edad]])) -> 8 | Q30: =IFERROR(LOOKUP(Titanic[[#This Row],[Edad Corrigida]],'Práctica 1'!$K$231:$K$240,'Práctica 1'!$L$231:$L$240), "DESCONOCIDO") -> DESCONOCIDO | R30: =Titanic[[#This Row],[Familia Horizontal]]+Titanic[[#This Row],[Familia Vertical]] -> 4
B31: 26 | C31: 1 | D31: 3 | E31: Asplund, Mrs. Carl Oscar (Selma Augusta Emilia Johansson) | F31: Mujer | G31: 38 | H31: 1 | I31: 5 | J31: 313875 | K31: 0 | L31: Southampton | M31: =IF(Titanic[[#This Row],[Sobrevive]]=1, "SOBREVIVE", "NO SOBREVIVE") -> SOBREVIVE | N31: =LOOKUP(Titanic[[#This Row],[Clase]],{1,2,3}, {"PRIMERA","SEGUNDA","TERCERA"}) -> TERCERA | O31: =IF(Titanic[[#This Row],[Sexo]]="Hombre", "HOMBRE", "MUJER") -> MUJER | P31: =IF(Titanic[[#This Row],[Edad]]="", "", IF(Titanic[[#This Row],[Edad]]>=100, Titanic[[#This Row],[Edad]] / 10, Titanic[[#This Row],[Edad]])) -> 38 | Q31: =IFERROR(LOOKUP(Titanic[[#This Row],[Edad Corrigida]],'Práctica 1'!$K$231:$K$240,'Práctica 1'!$L$231:$L$240), "DESCONOCIDO") -> 7. ADULTO 2 | R31: =Titanic[[#This Row],[Familia Horizontal]]+Titanic[[#This Row],[Familia Vertical]] -> 6
B32: 27 | C32: 0 | D32: 3 | E32: Emir, Mr. Farred Chehab | F32: Hombre | H32: 0 | I32: 0 | J32: 7225 | K32: 0 | L32: Cherburg | M32: =IF(Titanic[[#This Row],[Sobrevive]]=1, "SOBREVIVE", "NO SOBREVIVE") -> NO SOBREVIVE | N32: =LOOKUP(Titanic[[#This Row],[Clase]],{1,2,3}, {"PRIMERA","SEGUNDA","TERCERA"}) -> TERCERA | O32: =IF(Titanic[[#This Row],[Sexo]]="Hombre", "HOMBRE", "MUJER") -> HOMBRE | P32: =IF(Titanic[[#This Row],[Edad]]="", "", IF(Titanic[[#This Row],[Edad]]>=100, Titanic[[#This Row],[Edad]] / 10, Titanic[[#This Row],[Edad]])) | Q32: =IFERROR(LOOKUP(Titanic[[#This Row],[Edad Corrigida]],'Práctica 1'!$K$231:$K$240,'Práctica 1'!$L$231:$L$240), "DESCONOCIDO") -> DESCONOCIDO | R32: =Titanic[[#This Row],[Familia Horizontal]]+Titanic[[#This Row],[Familia Vertical]] -> 0
B33: 28 | C33: 0 | D33: 1 | E33: Fortune, Mr. Charles Alexander | F33: Hombre | G33: 19 | H33: 3 | I33: 2 | J33: 263 | K33: 1 | L33: Southampton | M33: =IF(Titanic[[#This Row],[Sobrevive]]=1, "SOBREVIVE", "NO SOBREVIVE") -> NO SOBREVIVE | N33: =LOOKUP(Titanic[[#This Row],[Clase]],{1,2,3}, {"PRIMERA","SEGUNDA","TERCERA"}) -> PRIMERA | O33: =IF(Titanic[[#This Row],[Sexo]]="Hombre", "HOMBRE", "MUJER") -> HOMBRE | P33: =IF(Titanic[[#This Row],[Edad]]="", "", IF(Titanic[[#This Row],[Edad]]>=100, Titanic[[#This Row],[Edad]] / 10, Titanic[[#This Row],[Edad]])) -> 19 | Q33: =IFERROR(LOOKUP(Titanic[[#This Row],[Edad Corrigida]],'Práctica 1'!$K$231:$K$240,'Práctica 1'!$L$231:$L$240), "DESCONOCIDO") -> 2. ADOLESCENTE | R33: =Titanic[[#This Row],[Familia Horizontal]]+Titanic[[#This Row],[Familia Vertical]] -> 5
B34: 29 | C34: 1 | D34: 3 | E34: O'Dwyer, Miss. Ellen "Nellie" | F34: Mujer | H34: 0 | I34: 0 | J34: 78792 | K34: 0 | L34: Queenstown | M34: =IF(Titanic[[#This Row],[Sobrevive]]=1, "SOBREVIVE", "NO SOBREVIVE") -> SOBREVIVE | N34: =LOOKUP(Titanic[[#This Row],[Clase]],{1,2,3}, {"PRIMERA","SEGUNDA","TERCERA"}) -> TERCERA | O34: =IF(Titanic[[#This Row],[Sexo]]="Hombre", "HOMBRE", "MUJER") -> MUJER | P34: =IF(Titanic[[#This Row],[Edad]]="", "", IF(Titanic[[#This Row],[Edad]]>=100, Titanic[[#This Row],[Edad]] / 10, Titanic[[#This Row],[Edad]])) | Q34: =IFERROR(LOOKUP(Titanic[[#This Row],[Edad Corrigida]],'Práctica 1'!$K$231:$K$240,'Práctica 1'!$L$231:$L$240), "DESCONOCIDO") -> DESCONOCIDO | R34: =Titanic[[#This Row],[Familia Horizontal]]+Titanic[[#This Row],[Familia Vertical]] -> 0
B35: 30 | C35: 0 | D35: 3 | E35: Todoroff, Mr. Lalio | F35: Hombre | H35: 0 | I35: 0 | J35: 78958 | K35: 0 | L35: Southampton | M35: =IF(Titanic[[#This Row],[Sobrevive]]=1, "SOBREVIVE", "NO SOBREVIVE") -> NO SOBREVIVE | N35: =LOOKUP(Titanic[[#This Row],[Clase]],{1,2,3}, {"PRIMERA","SEGUNDA","TERCERA"}) -> TERCERA | O35: =IF(Titanic[[#This Row],[Sexo]]="Hombre", "HOMBRE", "MUJER") -> HOMBRE | P35: =IF(Titanic[[#This Row],[Edad]]="", "", IF(Titanic[[#This Row],[Edad]]>=100, Titanic[[#This Row],[Edad]] / 10, Titanic[[#This Row],[Edad]])) | Q35: =IFERROR(LOOKUP(Titanic[[#This Row],[Edad Corrigida]],'Práctica 1'!$K$231:$K$240,'Práctica 1'!$L$231:$L$240), "DESCONOCIDO") -> DESCONOCIDO | R35: =Titanic[[#This Row],[Familia Horizontal]]+Titanic[[#This Row],[Familia Vertical]] -> 0
B36: 31 | C36: 0 | D36: 1 | E36: Uruchurtu, Don. Manuel E | F36: Hombre | G36: 40 | H36: 0 | I36: 0 | J36: 277208 | K36: 0 | L36: Cherburg | M36: =IF(Titanic[[#This Row],[Sobrevive]]=1, "SOBREVIVE", "NO SOBREVIVE") -> NO SOBREVIVE | N36: =LOOKUP(Titanic[[#This Row],[Clase]],{1,2,3}, {"PRIMERA","SEGUNDA","TERCERA"}) -> PRIMERA | O36: =IF(Titanic[[#This Row],[Sexo]]="Hombre", "HOMBRE", "MUJER") -> HOMBRE | P36: =IF(Titanic[[#This Row],[Edad]]="", "", IF(Titanic[[#This Row],[Edad]]>=100, Titanic[[#This Row],[Edad]] / 10, Titanic[[#This Row],[Edad]])) -> 40 | Q36: =IFERROR(LOOKUP(Titanic[[#This Row],[Edad Corrigida]],'Práctica 1'!$K$231:$K$240,'Práctica 1'!$L$231:$L$240), "DESCONOCIDO") -> 7. ADULTO 2 | R36: =Titanic[[#This Row],[Familia Horizontal]]+Titanic[[#This Row],[Familia Vertical]] -> 0
B37: 32 | C37: 1 | D37: 1 | E37: Spencer, Mrs. William Augustus (Marie Eugenie) | F37: Mujer | H37: 1 | I37: 0 | J37: 1465208 | K37: 1 | L37: Cherburg | M37: =IF(Titanic[[#This Row],[Sobrevive]]=1, "SOBREVIVE", "NO SOBREVIVE") -> SOBREVIVE | N37: =LOOKUP(Titanic[[#This Row],[Clase]],{1,2,3}, {"PRIMERA","SEGUNDA","TERCERA"}) -> PRIMERA | O37: =IF(Titanic[[#This Row],[Sexo]]="Hombre", "HOMBRE", "MUJER") -> MUJER | P37: =IF(Titanic[[#This Row],[Edad]]="", "", IF(Titanic[[#This Row],[Edad]]>=100, Titanic[[#This Row],[Edad]] / 10, Titanic[[#This Row],[Edad]])) | Q37: =IFERROR(LOOKUP(Titanic[[#This Row],[Edad Corrigida]],'Práctica 1'!$K$231:$K$240,'Práctica 1'!$L$231:$L$240), "DESCONOCIDO") -> DESCONOCIDO | R37: =Titanic[[#This Row],[Familia Horizontal]]+Titanic[[#This Row],[Familia Vertical]] -> 1
B38: 33 | C38: 1 | D38: 3 | E38: Glynn, Miss. Mary Agatha | F38: Mujer | H38: 0 | I38: 0 | J38: 775 | K38: 0 | L38: Queenstown | M38: =IF(Titanic[[#This Row],[Sobrevive]]=1, "SOBREVIVE", "NO SOBREVIVE") -> SOBREVIVE | N38: =LOOKUP(Titanic[[#This Row],[Clase]],{1,2,3}, {"PRIMERA","SEGUNDA","TERCERA"}) -> TERCERA | O38: =IF(Titanic[[#This Row],[Sexo]]="Hombre", "HOMBRE", "MUJER") -> MUJER | P38: =IF(Titanic[[#This Row],[Edad]]="", "", IF(Titanic[[#This Row],[Edad]]>=100, Titanic[[#This Row],[Edad]] / 10, Titanic[[#This Row],[Edad]])) | Q38: =IFERROR(LOOKUP(Titanic[[#This Row],[Edad Corrigida]],'Práctica 1'!$K$231:$K$240,'Práctica 1'!$L$231:$L$240), "DESCONOCIDO") -> DESCONOCIDO | R38: =Titanic[[#This Row],[Familia Horizontal]]+Titanic[[#This Row],[Familia Vertical]] -> 0
B39: 34 | C39: 0 | D39: 2 | E39: Wheadon, Mr. Edward H | F39: Hombre | G39: 66 | H39: 0 | I39: 0 | J39: 105 | K39: 0 | L39: Southampton | M39: =IF(Titanic[[#This Row],[Sobrevive]]=1, "SOBREVIVE", "NO SOBREVIVE") -> NO SOBREVIVE | N39: =LOOKUP(Titanic[[#This Row],[Clase]],{1,2,3}, {"PRIMERA","SEGUNDA","TERCERA"}) -> SEGUNDA | O39: =IF(Titanic[[#This Row],[Sexo]]="Hombre", "HOMBRE", "MUJER") -> HOMBRE | P39: =IF(Titanic[[#This Row],[Edad]]="", "", IF(Titanic[[#This Row],[Edad]]>=100, Titanic[[#This Row],[Edad]] / 10, Titanic[[#This Row],[Edad]])) -> 66 | Q39: =IFERROR(LOOKUP(Titanic[[#This Row],[Edad Corrigida]],'Práctica 1'!$K$231:$K$240,'Práctica 1'!$L$231:$L$240), "DESCONOCIDO") -> 9. ADULTO 4 | R39: =Titanic[[#This Row],[Familia Horizontal]]+Titanic[[#This Row],[Familia Vertical]] -> 0
B40: 35 | C40: 0 | D40: 1 | E40: Meyer, Mr. Edgar Joseph | F40: Hombre | G40: 28 | H40: 1 | I40: 0 | J40: 821708 | K40: 0 | L40: Cherburg | M40: =IF(Titanic[[#This Row],[Sobrevive]]=1, "SOBREVIVE", "NO SOBREVIVE") -> NO SOBREVIVE | N40: =LOOKUP(Titanic[[#This Row],[Clase]],{1,2,3}, {"PRIMERA","SEGUNDA","TERCERA"}) -> PRIMERA | O40: =IF(Titanic[[#This Row],[Sexo]]="Hombre", "HOMBRE", "MUJER") -> HOMBRE | P40: =IF(Titanic[[#This Row],[Edad]]="", "", IF(Titanic[[#This Row],[Edad]]>=100, Titanic[[#This Row],[Edad]] / 10, Titanic[[#This Row],[Edad]])) -> 28 | Q40: =IFERROR(LOOKUP(Titanic[[#This Row],[Edad Corrigida]],'Práctica 1'!$K$231:$K$240,'Práctica 1'!$L$231:$L$240), "DESCONOCIDO") -> 4. ADULTO JOVEN | R40: =Titanic[[#This Row],[Familia Horizontal]]+Titanic[[#This Row],[Familia Vertical]] -> 1
B41: 36 | C41: 0 | D41: 1 | E41: Holverson, Mr. Alexander Oskar | F41: Hombre | G41: 42 | H41: 1 | I41: 0 | J41: 52 | K41: 0 | L41: Southampton | M41: =IF(Titanic[[#This Row],[Sobrevive]]=1, "SOBREVIVE", "NO SOBREVIVE") -> NO SOBREVIVE | N41: =LOOKUP(Titanic[[#This Row],[Clase]],{1,2,3}, {"PRIMERA","SEGUNDA","TERCERA"}) -> PRIMERA | O41: =IF(Titanic[[#This Row],[Sexo]]="Hombre", "HOMBRE", "MUJER") -> HOMBRE | P41: =IF(Titanic[[#This Row],[Edad]]="", "", IF(Titanic[[#This Row],[Edad]]>=100, Titanic[[#This Row],[Edad]] / 10, Titanic[[#This Row],[Edad]])) -> 42 | Q41: =IFERROR(LOOKUP(Titanic[[#This Row],[Edad Corrigida]],'Práctica 1'!$K$231:$K$240,'Práctica 1'!$L$231:$L$240), "DESCONOCIDO") -> 8. ADULTO 3 | R41: =Titanic[[#This Row],[Familia Horizontal]]+Titanic[[#This Row],[Familia Vertical]] -> 1
B42: 37 | C42: 1 | D42: 3 | E42: Mamee, Mr. Hanna | F42: Hombre | H42: 0 | I42: 0 | J42: 72292 | K42: 0 | L42: Cherburg | M42: =IF(Titanic[[#This Row],[Sobrevive]]=1, "SOBREVIVE", "NO SOBREVIVE") -> SOBREVIVE | N42: =LOOKUP(Titanic[[#This Row],[Clase]],{1,2,3}, {"PRIMERA","SEGUNDA","TERCERA"}) -> TERCERA | O42: =IF(Titanic[[#This Row],[Sexo]]="Hombre", "HOMBRE", "MUJER") -> HOMBRE | P42: =IF(Titanic[[#This Row],[Edad]]="", "", IF(Titanic[[#This Row],[Edad]]>=100, Titanic[[#This Row],[Edad]] / 10, Titanic[[#This Row],[Edad]])) | Q42: =IFERROR(LOOKUP(Titanic[[#This Row],[Edad Corrigida]],'Práctica 1'!$K$231:$K$240,'Práctica 1'!$L$231:$L$240), "DESCONOCIDO") -> DESCONOCIDO | R42: =Titanic[[#This Row],[Familia Horizontal]]+Titanic[[#This Row],[Familia Vertical]] -> 0
B43: 38 | C43: 0 | D43: 3 | E43: Cann, Mr. Ernest Charles | F43: Hombre | G43: 21 | H43: 0 | I43: 0 | J43: 805 | K43: 0 | L43: Southampton | M43: =IF(Titanic[[#This Row],[Sobrevive]]=1, "SOBREVIVE", "NO SOBREVIVE") -> NO SOBREVIVE | N43: =LOOKUP(Titanic[[#This Row],[Clase]],{1,2,3}, {"PRIMERA","SEGUNDA","TERCERA"}) -> TERCERA | O43: =IF(Titanic[[#This Row],[Sexo]]="Hombre", "HOMBRE", "MUJER") -> HOMBRE | P43: =IF(Titanic[[#This Row],[Edad]]="", "", IF(Titanic[[#This Row],[Edad]]>=100, Titanic[[#This Row],[Edad]] / 10, Titanic[[#This Row],[Edad]])) -> 21 | Q43: =IFERROR(LOOKUP(Titanic[[#This Row],[Edad Corrigida]],'Práctica 1'!$K$231:$K$240,'Práctica 1'!$L$231:$L$240), "DESCONOCIDO") -> 2. ADOLESCENTE | R43: =Titanic[[#This Row],[Familia Horizontal]]+Titanic[[#This Row],[Familia Vertical]] -> 0
B44: 39 | C44: 0 | D44: 3 | E44: Vander Planke, Miss. Augusta Maria | F44: Mujer | G44: 18 | H44: 2 | I44: 0 | J44: 18 | K44: 0 | L44: Southampton | M44: =IF(Titanic[[#This Row],[Sobrevive]]=1, "SOBREVIVE", "NO SOBREVIVE") -> NO SOBREVIVE | N44: =LOOKUP(Titanic[[#This Row],[Clase]],{1,2,3}, {"PRIMERA","SEGUNDA","TERCERA"}) -> TERCERA | O44: =IF(Titanic[[#This Row],[Sexo]]="Hombre", "HOMBRE", "MUJER") -> MUJER | P44: =IF(Titanic[[#This Row],[Edad]]="", "", IF(Titanic[[#This Row],[Edad]]>=100, Titanic[[#This Row],[Edad]] / 10, Titanic[[#This Row],[Edad]])) -> 18 | Q44: =IFERROR(LOOKUP(Titanic[[#This Row],[Edad Corrigida]],'Práctica 1'!$K$231:$K$240,'Práctica 1'!$L$231:$L$240), "DESCONOCIDO") -> 1. INFANTE | R44: =Titanic[[#This Row],[Familia Horizontal]]+Titanic[[#This Row],[Familia Vertical]] -> 2
B45: 40 | C45: 1 | D45: 3 | E45: Nicola-Yarred, Miss. Jamila | F45: Mujer | G45: 14 | H45: 1 | I45: 0 | J45: 112417 | K45: 0 | L45: Cherburg | M45: =IF(Titanic[[#This Row],[Sobrevive]]=1, "SOBREVIVE", "NO SOBREVIVE") -> SOBREVIVE | N45: =LOOKUP(Titanic[[#This Row],[Clase]],{1,2,3}, {"PRIMERA","SEGUNDA","TERCERA"}) -> TERCERA | O45: =IF(Titanic[[#This Row],[Sexo]]="Hombre", "HOMBRE", "MUJER") -> MUJER | P45: =IF(Titanic[[#This Row],[Edad]]="", "", IF(Titanic[[#This Row],[Edad]]>=100, Titanic[[#This Row],[Edad]] / 10, Titanic[[#This Row],[Edad]])) -> 14 | Q45: =IFERROR(LOOKUP(Titanic[[#This Row],[Edad Corrigida]],'Práctica 1'!$K$231:$K$240,'Práctica 1'!$L$231:$L$240), "DESCONOCIDO") -> DESCONOCIDO | R45: =Titanic[[#This Row],[Familia Horizontal]]+Titanic[[#This Row],[Familia Vertical]] -> 1
B46: 41 | C46: 0 | D46: 3 | E46: Ahlin, Mrs. Johan (Johanna Persdotter Larsson) | F46: Mujer | G46: 40 | H46: 1 | I46: 0 | J46: 9475 | K46: 0 | L46: Southampton | M46: =IF(Titanic[[#This Row],[Sobrevive]]=1, "SOBREVIVE", "NO SOBREVIVE") -> NO SOBREVIVE | N46: =LOOKUP(Titanic[[#This Row],[Clase]],{1,2,3}, {"PRIMERA","SEGUNDA","TERCERA"}) -> TERCERA | O46: =IF(Titanic[[#This Row],[Sexo]]="Hombre", "HOMBRE", "MUJER") -> MUJER | P46: =IF(Titanic[[#This Row],[Edad]]="", "", IF(Titanic[[#This Row],[Edad]]>=100, Titanic[[#This Row],[Edad]] / 10, Titanic[[#This Row],[Edad]])) -> 40 | Q46: =IFERROR(LOOKUP(Titanic[[#This Row],[Edad Corrigida]],'Práctica 1'!$K$231:$K$240,'Práctica 1'!$L$231:$L$240), "DESCONOCIDO") -> 7. ADULTO 2 | R46: =Titanic[[#This Row],[Familia Horizontal]]+Titanic[[#This Row],[Familia Vertical]] -> 1
B47: 42 | C47: 0 | D47: 2 | E47: Turpin, Mrs. William John Robert (Dorothy Ann Wonnacott) | F47: Mujer | G47: 27 | H47: 1 | I47: 0 | J47: 21 | K47: 0 | L47: Southampton | M47: =IF(Titanic[[#This Row],[Sobrevive]]=1, "SOBREVIVE", "NO SOBREVIVE") -> NO SOBREVIVE | N47: =LOOKUP(Titanic[[#This Row],[Clase]],{1,2,3}, {"PRIMERA","SEGUNDA","TERCERA"}) -> SEGUNDA | O47: =IF(Titanic[[#This Row],[Sexo]]="Hombre", "HOMBRE", "MUJER") -> MUJER | P47: =IF(Titanic[[#This Row],[Edad]]="", "", IF(Titanic[[#This Row],[Edad]]>=100, Titanic[[#This Row],[Edad]] / 10, Titanic[[#This Row],[Edad]])) -> 27 | Q47: =IFERROR(LOOKUP(Titanic[[#This Row],[Edad Corrigida]],'Práctica 1'!$K$231:$K$240,'Práctica 1'!$L$231:$L$240), "DESCONOCIDO") -> 4. ADULTO JOVEN | R47: =Titanic[[#This Row],[Familia Horizontal]]+Titanic[[#This Row],[Familia Vertical]] -> 1
B48: 43 | C48: 0 | D48: 3 | E48: Kraeff, Mr. Theodor | F48: Hombre | H48: 0 | I48: 0 | J48: 78958 | K48: 0 | L48: Cherburg | M48: =IF(Titanic[[#This Row],[Sobrevive]]=1, "SOBREVIVE", "NO SOBREVIVE") -> NO SOBREVIVE | N48: =LOOKUP(Titanic[[#This Row],[Clase]],{1,2,3}, {"PRIMERA","SEGUNDA","TERCERA"}) -> TERCERA | O48: =IF(Titanic[[#This Row],[Sexo]]="Hombre", "HOMBRE", "MUJER") -> HOMBRE | P48: =IF(Titanic[[#This Row],[Edad]]="", "", IF(Titanic[[#This Row],[Edad]]>=100, Titanic[[#This Row],[Edad]] / 10, Titanic[[#This Row],[Edad]])) | Q48: =IFERROR(LOOKUP(Titanic[[#This Row],[Edad Corrigida]],'Práctica 1'!$K$231:$K$240,'Práctica 1'!$L$231:$L$240), "DESCONOCIDO") -> DESCONOCIDO | R48: =Titanic[[#This Row],[Familia Horizontal]]+Titanic[[#This Row],[Familia Vertical]] -> 0
B49: 44 | C49: 1 | D49: 2 | E49: Laroche, Miss. Simonne Marie Anne Andree | F49: Mujer | G49: 3 | H49: 1 | I49: 2 | J49: 415792 | K49: 0 | L49: Cherburg | M49: =IF(Titanic[[#This Row],[Sobrevive]]=1, "SOBREVIVE", "NO SOBREVIVE") -> SOBREVIVE | N49: =LOOKUP(Titanic[[#This Row],[Clase]],{1,2,3}, {"PRIMERA","SEGUNDA","TERCERA"}) -> SEGUNDA | O49: =IF(Titanic[[#This Row],[Sexo]]="Hombre", "HOMBRE", "MUJER") -> MUJER | P49: =IF(Titanic[[#This Row],[Edad]]="", "", IF(Titanic[[#This Row],[Edad]]>=100, Titanic[[#This Row],[Edad]] / 10, Titanic[[#This Row],[Edad]])) -> 3 | Q49: =IFERROR(LOOKUP(Titanic[[#This Row],[Edad Corrigida]],'Práctica 1'!$K$231:$K$240,'Práctica 1'!$L$231:$L$240), "DESCONOCIDO") -> DESCONOCIDO | R49: =Titanic[[#This Row],[Familia Horizontal]]+Titanic[[#This Row],[Familia Vertical]] -> 3
B50: 45 | C50: 1 | D50: 3 | E50: Devaney, Miss. Margaret Delia | F50: Mujer | G50: 19 | H50: 0 | I50: 0 | J50: 78792 | K50: 0 | L50: Queenstown | M50: =IF(Titanic[[#This Row],[Sobrevive]]=1, "SOBREVIVE", "NO SOBREVIVE") -> SOBREVIVE | N50: =LOOKUP(Titanic[[#This Row],[Clase]],{1,2,3}, {"PRIMERA","SEGUNDA","TERCERA"}) -> TERCERA | O50: =IF(Titanic[[#This Row],[Sexo]]="Hombre", "HOMBRE", "MUJER") -> MUJER | P50: =IF(Titanic[[#This Row],[Edad]]="", "", IF(Titanic[[#This Row],[Edad]]>=100, Titanic[[#This Row],[Edad]] / 10, Titanic[[#This Row],[Edad]])) -> 19 | Q50: =IFERROR(LOOKUP(Titanic[[#This Row],[Edad Corrigida]],'Práctica 1'!$K$231:$K$240,'Práctica 1'!$L$231:$L$240), "DESCONOCIDO") -> 2. ADOLESCENTE | R50: =Titanic[[#This Row],[Familia Horizontal]]+Titanic[[#This Row],[Familia Vertical]] -> 0
B51: 46 | C51: 0 | D51: 3 | E51: Rogers, Mr. William John | F51: Hombre | H51: 0 | I51: 0 | J51: 805 | K51: 0 | L51: Southampton | M51: =IF(Titanic[[#This Row],[Sobrevive]]=1, "SOBREVIVE", "NO SOBREVIVE") -> NO SOBREVIVE | N51: =LOOKUP(Titanic[[#This Row],[Clase]],{1,2,3}, {"PRIMERA","SEGUNDA","TERCERA"}) -> TERCERA | O51: =IF(Titanic[[#This Row],[Sexo]]="Hombre", "HOMBRE", "MUJER") -> HOMBRE | P51: =IF(Titanic[[#This Row],[Edad]]="", "", IF(Titanic[[#This Row],[Edad]]>=100, Titanic[[#This Row],[Edad]] / 10, Titanic[[#This Row],[Edad]])) | Q51: =IFERROR(LOOKUP(Titanic[[#This Row],[Edad Corrigida]],'Práctica 1'!$K$231:$K$240,'Práctica 1'!$L$231:$L$240), "DESCONOCIDO") -> DESCONOCIDO | R51: =Titanic[[#This Row],[Familia Horizontal]]+Titanic[[#This Row],[Familia Vertical]] -> 0
B52: 47 | C52: 0 | D52: 3 | E52: Lennon, Mr. Denis | F52: Hombre | H52: 1 | I52: 0 | J52: 155 | K52: 0 | L52: Queenstown | M52: =IF(Titanic[[#This Row],[Sobrevive]]=1, "SOBREVIVE", "NO SOBREVIVE") -> NO SOBREVIVE | N52: =LOOKUP(Titanic[[#This Row],[Clase]],{1,2,3}, {"PRIMERA","SEGUNDA","TERCERA"}) -> TERCERA | O52: =IF(Titanic[[#This Row],[Sexo]]="Hombre", "HOMBRE", "MUJER") -> HOMBRE | P52: =IF(Titanic[[#This Row],[Edad]]="", "", IF(Titanic[[#This Row],[Edad]]>=100, Titanic[[#This Row],[Edad]] / 10, Titanic[[#This Row],[Edad]])) | Q52: =IFERROR(LOOKUP(Titanic[[#This Row],[Edad Corrigida]],'Práctica 1'!$K$231:$K$240,'Práctica 1'!$L$231:$L$240), "DESCONOCIDO") -> DESCONOCIDO | R52: =Titanic[[#This Row],[Familia Horizontal]]+Titanic[[#This Row],[Familia Vertical]] -> 1
B53: 48 | C53: 1 | D53: 3 | E53: O'Driscoll, Miss. Bridget | F53: Mujer | H53: 0 | I53: 0 | J53: 775 | K53: 0 | L53: Queenstown | M53: =IF(Titanic[[#This Row],[Sobrevive]]=1, "SOBREVIVE", "NO SOBREVIVE") -> SOBREVIVE | N53: =LOOKUP(Titanic[[#This Row],[Clase]],{1,2,3}, {"PRIMERA","SEGUNDA","TERCERA"}) -> TERCERA | O53: =IF(Titanic[[#This Row],[Sexo]]="Hombre", "HOMBRE", "MUJER") -> MUJER | P53: =IF(Titanic[[#This Row],[Edad]]="", "", IF(Titanic[[#This Row],[Edad]]>=100, Titanic[[#This Row],[Edad]] / 10, Titanic[[#This Row],[Edad]])) | Q53: =IFERROR(LOOKUP(Titanic[[#This Row],[Edad Corrigida]],'Práctica 1'!$K$231:$K$240,'Práctica 1'!$L$231:$L$240), "DESCONOCIDO") -> DESCONOCIDO | R53: =Titanic[[#This Row],[Familia Horizontal]]+Titanic[[#This Row],[Familia Vertical]] -> 0
B54: 49 | C54: 0 | D54: 3 | E54: Samaan, Mr. Youssef | F54: Hombre | H54: 2 | I54: 0 | J54: 216792 | K54: 0 | L54: Cherburg | M54: =IF(Titanic[[#This Row],[Sobrevive]]=1, "SOBREVIVE", "NO SOBREVIVE") -> NO SOBREVIVE | N54: =LOOKUP(Titanic[[#This Row],[Clase]],{1,2,3}, {"PRIMERA","SEGUNDA","TERCERA"}) -> TERCERA | O54: =IF(Titanic[[#This Row],[Sexo]]="Hombre", "HOMBRE", "MUJER") -> HOMBRE | P54: =IF(Titanic[[#This Row],[Edad]]="", "", IF(Titanic[[#This Row],[Edad]]>=100, Titanic[[#This Row],[Edad]] / 10, Titanic[[#This Row],[Edad]])) | Q54: =IFERROR(LOOKUP(Titanic[[#This Row],[Edad Corrigida]],'Práctica 1'!$K$231:$K$240,'Práctica 1'!$L$231:$L$240), "DESCONOCIDO") -> DESCONOCIDO | R54: =Titanic[[#This Row],[Familia Horizontal]]+Titanic[[#This Row],[Familia Vertical]] -> 2
B55: 50 | C55: 0 | D55: 3 | E55: Arnold-Franchi, Mrs. Josef (Josefine Franchi) | F55: Mujer | G55: 18 | H55: 1 | I55: 0 | J55: 178 | K55: 0 | L55: Southampton | M55: =IF(Titanic[[#This Row],[Sobrevive]]=1, "SOBREVIVE", "NO SOBREVIVE") -> NO SOBREVIVE | N55: =LOOKUP(Titanic[[#This Row],[Clase]],{1,2,3}, {"PRIMERA","SEGUNDA","TERCERA"}) -> TERCERA | O55: =IF(Titanic[[#This Row],[Sexo]]="Hombre", "HOMBRE", "MUJER") -> MUJER | P55: =IF(Titanic[[#This Row],[Edad]]="", "", IF(Titanic[[#This Row],[Edad]]>=100, Titanic[[#This Row],[Edad]] / 10, Titanic[[#This Row],[Edad]])) -> 18 | Q55: =IFERROR(LOOKUP(Titanic[[#This Row],[Edad Corrigida]],'Práctica 1'!$K$231:$K$240,'Práctica 1'!$L$231:$L$240), "DESCONOCIDO") -> 1. INFANTE | R55: =Titanic[[#This Row],[Familia Horizontal]]+Titanic[[#This Row],[Familia Vertical]] -> 1
B56: 51 | C56: 0 | D56: 3 | E56: Panula, Master. Juha Niilo | F56: Hombre | G56: 7 | H56: 4 | I56: 1 | J56: 396875 | K56: 0 | L56: Southampton | M56: =IF(Titanic[[#This Row],[Sobrevive]]=1, "SOBREVIVE", "NO SOBREVIVE") -> NO SOBREVIVE | N56: =LOOKUP(Titanic[[#This Row],[Clase]],{1,2,3}, {"PRIMERA","SEGUNDA","TERCERA"}) -> TERCERA | O56: =IF(Titanic[[#This Row],[Sexo]]="Hombre", "HOMBRE", "MUJER") -> HOMBRE | P56: =IF(Titanic[[#This Row],[Edad]]="", "", IF(Titanic[[#This Row],[Edad]]>=100, Titanic[[#This Row],[Edad]] / 10, Titanic[[#This Row],[Edad]])) -> 7 | Q56: =IFERROR(LOOKUP(Titanic[[#This Row],[Edad Corrigida]],'Práctica 1'!$K$231:$K$240,'Práctica 1'!$L$231:$L$240), "DESCONOCIDO") -> DESCONOCIDO | R56: =Titanic[[#This Row],[Familia Horizontal]]+Titanic[[#This Row],[Familia Vertical]] -> 5
B57: 52 | C57: 0 | D57: 3 | E57: Nosworthy, Mr. Richard Cater | F57: Hombre | G57: 21 | H57: 0 | I57: 0 | J57: 78 | K57: 0 | L57: Southampton | M57: =IF(Titanic[[#This Row],[Sobrevive]]=1, "SOBREVIVE", "NO SOBREVIVE") -> NO SOBREVIVE | N57: =LOOKUP(Titanic[[#This Row],[Clase]],{1,2,3}, {"PRIMERA","SEGUNDA","TERCERA"}) -> TERCERA | O57: =IF(Titanic[[#This Row],[Sexo]]="Hombre", "HOMBRE", "MUJER") -> HOMBRE | P57: =IF(Titanic[[#This Row],[Edad]]="", "", IF(Titanic[[#This Row],[Edad]]>=100, Titanic[[#This Row],[Edad]] / 10, Titanic[[#This Row],[Edad]])) -> 21 | Q57: =IFERROR(LOOKUP(Titanic[[#This Row],[Edad Corrigida]],'Práctica 1'!$K$231:$K$240,'Práctica 1'!$L$231:$L$240), "DESCONOCIDO") -> 2. ADOLESCENTE | R57: =Titanic[[#This Row],[Familia Horizontal]]+Titanic[[#This Row],[Familia Vertical]] -> 0
B58: 53 | C58: 1 | D58: 1 | E58: Harper, Mrs. Henry Sleeper (Myna Haxtun) | F58: Mujer | G58: 49 | H58: 1 | I58: 0 | J58: 767292 | K58: 1 | L58: Cherburg | M58: =IF(Titanic[[#This Row],[Sobrevive]]=1, "SOBREVIVE", "NO SOBREVIVE") -> SOBREVIVE | N58: =LOOKUP(Titanic[[#This Row],[Clase]],{1,2,3}, {"PRIMERA","SEGUNDA","TERCERA"}) -> PRIMERA | O58: =IF(Titanic[[#This Row],[Sexo]]="Hombre", "HOMBRE", "MUJER") -> MUJER | P58: =IF(Titanic[[#This Row],[Edad]]="", "", IF(Titanic[[#This Row],[Edad]]>=100, Titanic[[#This Row],[Edad]] / 10, Titanic[[#This Row],[Edad]])) -> 49 | Q58: =IFERROR(LOOKUP(Titanic[[#This Row],[Edad Corrigida]],'Práctica 1'!$K$231:$K$240,'Práctica 1'!$L$231:$L$240), "DESCONOCIDO") -> 8. ADULTO 3 | R58: =Titanic[[#This Row],[Familia Horizontal]]+Titanic[[#This Row],[Familia Vertical]] -> 1
B59: 54 | C59: 1 | D59: 2 | E59: Faunthorpe, Mrs. Lizzie (Elizabeth Anne Wilkinson) | F59: Mujer | G59: 29 | H59: 1 | I59: 0 | J59: 26 | K59: 0 | L59: Southampton | M59: =IF(Titanic[[#This Row],[Sobrevive]]=1, "SOBREVIVE", "NO SOBREVIVE") -> SOBREVIVE | N59: =LOOKUP(Titanic[[#This Row],[Clase]],{1,2,3}, {"PRIMERA","SEGUNDA","TERCERA"}) -> SEGUNDA | O59: =IF(Titanic[[#This Row],[Sexo]]="Hombre", "HOMBRE", "MUJER") -> MUJER | P59: =IF(Titanic[[#This Row],[Edad]]="", "", IF(Titanic[[#This Row],[Edad]]>=100, Titanic[[#This Row],[Edad]] / 10, Titanic[[#This Row],[Edad]])) -> 29 | Q59: =IFERROR(LOOKUP(Titanic[[#This Row],[Edad Corrigida]],'Práctica 1'!$K$231:$K$240,'Práctica 1'!$L$231:$L$240), "DESCONOCIDO") -> 5. ADULTO | R59: =Titanic[[#This Row],[Familia Horizontal]]+Titanic[[#This Row],[Familia Vertical]] -> 1
B60: 55 | C60: 0 | D60: 1 | E60: Ostby, Mr. Engelhart Cornelius | F60: Hombre | G60: 65 | H60: 0 | I60: 1 | J60: 619792 | K60: 1 | L60: Cherburg | M60: =IF(Titanic[[#This Row],[Sobrevive]]=1, "SOBREVIVE", "NO SOBREVIVE") -> NO SOBREVIVE | N60: =LOOKUP(Titanic[[#This Row],[Clase]],{1,2,3}, {"PRIMERA","SEGUNDA","TERCERA"}) -> PRIMERA | O60: =IF(Titanic[[#This Row],[Sexo]]="Hombre", "HOMBRE", "MUJER") -> HOMBRE | P60: =IF(Titanic[[#This Row],[Edad]]="", "", IF(Titanic[[#This Row],[Edad]]>=100, Titanic[[#This Row],[Edad]] / 10, Titanic[[#This Row],[Edad]])) -> 65 | Q60: =IFERROR(LOOKUP(Titanic[[#This Row],[Edad Corrigida]],'Práctica 1'!$K$231:$K$240,'Práctica 1'!$L$231:$L$240), "DESCONOCIDO") -> 9. ADULTO 4 | R60: =Titanic[[#This Row],[Familia Horizontal]]+Titanic[[#This Row],[Familia Vertical]] -> 1
B61: 56 | C61: 1 | D61: 1 | E61: Woolner, Mr. Hugh | F61: Hombre | H61: 0 | I61: 0 | J61: 355 | K61: 1 | L61: Southampton | M61: =IF(Titanic[[#This Row],[Sobrevive]]=1, "SOBREVIVE", "NO SOBREVIVE") -> SOBREVIVE | N61: =LOOKUP(Titanic[[#This Row],[Clase]],{1,2,3}, {"PRIMERA","SEGUNDA","TERCERA"}) -> PRIMERA | O61: =IF(Titanic[[#This Row],[Sexo]]="Hombre", "HOMBRE", "MUJER") -> HOMBRE | P61: =IF(Titanic[[#This Row],[Edad]]="", "", IF(Titanic[[#This Row],[Edad]]>=100, Titanic[[#This Row],[Edad]] / 10, Titanic[[#This Row],[Edad]])) | Q61: =IFERROR(LOOKUP(Titanic[[#This Row],[Edad Corrigida]],'Práctica 1'!$K$231:$K$240,'Práctica 1'!$L$231:$L$240), "DESCONOCIDO") -> DESCONOCIDO | R61: =Titanic[[#This Row],[Familia Horizontal]]+Titanic[[#This Row],[Familia Vertical]] -> 0
B62: 57 | C62: 1 | D62: 2 | E62: Rugg, Miss. Emily | F62: Mujer | G62: 21 | H62: 0 | I62: 0 | J62: 105 | K62: 0 | L62: Southampton | M62: =IF(Titanic[[#This Row],[Sobrevive]]=1, "SOBREVIVE", "NO SOBREVIVE") -> SOBREVIVE | N62: =LOOKUP(Titanic[[#This Row],[Clase]],{1,2,3}, {"PRIMERA","SEGUNDA","TERCERA"}) -> SEGUNDA | O62: =IF(Titanic[[#This Row],[Sexo]]="Hombre", "HOMBRE", "MUJER") -> MUJER | P62: =IF(Titanic[[#This Row],[Edad]]="", "", IF(Titanic[[#This Row],[Edad]]>=100, Titanic[[#This Row],[Edad]] / 10, Titanic[[#This Row],[Edad]])) -> 21 | Q62: =IFERROR(LOOKUP(Titanic[[#This Row],[Edad Corrigida]],'Práctica 1'!$K$231:$K$240,'Práctica 1'!$L$231:$L$240), "DESCONOCIDO") -> 2. ADOLESCENTE | R62: =Titanic[[#This Row],[Familia Horizontal]]+Titanic[[#This Row],[Familia Vertical]] -> 0
B63: 58 | C63: 0 | D63: 3 | E63: Novel, Mr. Mansouer | F63: Hombre | G63: 285 | H63: 0 | I63: 0 | J63: 72292 | K63: 0 | L63: Cherburg | M63: =IF(Titanic[[#This Row],[Sobrevive]]=1, "SOBREVIVE", "NO SOBREVIVE") -> NO SOBREVIVE | N63: =LOOKUP(Titanic[[#This Row],[Clase]],{1,2,3}, {"PRIMERA","SEGUNDA","TERCERA"}) -> TERCERA | O63: =IF(Titanic[[#This Row],[Sexo]]="Hombre", "HOMBRE", "MUJER") -> HOMBRE | P63: =IF(Titanic[[#This Row],[Edad]]="", "", IF(Titanic[[#This Row],[Edad]]>=100, Titanic[[#This Row],[Edad]] / 10, Titanic[[#This Row],[Edad]])) -> 28.5 | Q63: =IFERROR(LOOKUP(Titanic[[#This Row],[Edad Corrigida]],'Práctica 1'!$K$231:$K$240,'Práctica 1'!$L$231:$L$240), "DESCONOCIDO") -> 4. ADULTO JOVEN | R63: =Titanic[[#This Row],[Familia Horizontal]]+Titanic[[#This Row],[Familia Vertical]] -> 0
B64: 59 | C64: 1 | D64: 2 | E64: West, Miss. Constance Mirium | F64: Mujer | G64: 5 | H64: 1 | I64: 2 | J64: 2775 | K64: 0 | L64: Southampton | M64: =IF(Titanic[[#This Row],[Sobrevive]]=1, "SOBREVIVE", "NO SOBREVIVE") -> SOBREVIVE | N64: =LOOKUP(Titanic[[#This Row],[Clase]],{1,2,3}, {"PRIMERA","SEGUNDA","TERCERA"}) -> SEGUNDA | O64: =IF(Titanic[[#This Row],[Sexo]]="Hombre", "HOMBRE", "MUJER") -> MUJER | P64: =IF(Titanic[[#This Row],[Edad]]="", "", IF(Titanic[[#This Row],[Edad]]>=100, Titanic[[#This Row],[Edad]] / 10, Titanic[[#This Row],[Edad]])) -> 5 | Q64: =IFERROR(LOOKUP(Titanic[[#This Row],[Edad Corrigida]],'Práctica 1'!$K$231:$K$240,'Práctica 1'!$L$231:$L$240), "DESCONOCIDO") -> DESCONOCIDO | R64: =Titanic[[#This Row],[Familia Horizontal]]+Titanic[[#This Row],[Familia Vertical]] -> 3
B65: 60 | C65: 0 | D65: 3 | E65: Goodwin, Master. William Frederick | F65: Hombre | G65: 11 | H65: 5 | I65: 2 | J65: 469 | K65: 0 | L65: Southampton | M65: =IF(Titanic[[#This Row],[Sobrevive]]=1, "SOBREVIVE", "NO SOBREVIVE") -> NO SOBREVIVE | N65: =LOOKUP(Titanic[[#This Row],[Clase]],{1,2,3}, {"PRIMERA","SEGUNDA","TERCERA"}) -> TERCERA | O65: =IF(Titanic[[#This Row],[Sexo]]="Hombre", "HOMBRE", "MUJER") -> HOMBRE | P65: =IF(Titanic[[#This Row],[Edad]]="", "", IF(Titanic[[#This Row],[Edad]]>=100, Titanic[[#This Row],[Edad]] / 10, Titanic[[#This Row],[Edad]])) -> 11 | Q65: =IFERROR(LOOKUP(Titanic[[#This Row],[Edad Corrigida]],'Práctica 1'!$K$231:$K$240,'Práctica 1'!$L$231:$L$240), "DESCONOCIDO") -> DESCONOCIDO | R65: =Titanic[[#This Row],[Familia Horizontal]]+Titanic[[#This Row],[Familia Vertical]] -> 7
B66: 61 | C66: 0 | D66: 3 | E66: Sirayanian, Mr. Orsen | F66: Hombre | G66: 22 | H66: 0 | I66: 0 | J66: 72292 | K66: 0 | L66: Cherburg | M66: =IF(Titanic[[#This Row],[Sobrevive]]=1, "SOBREVIVE", "NO SOBREVIVE") -> NO SOBREVIVE | N66: =LOOKUP(Titanic[[#This Row],[Clase]],{1,2,3}, {"PRIMERA","SEGUNDA","TERCERA"}) -> TERCERA | O66: =IF(Titanic[[#This Row],[Sexo]]="Hombre", "HOMBRE", "MUJER") -> HOMBRE | P66: =IF(Titanic[[#This Row],[Edad]]="", "", IF(Titanic[[#This Row],[Edad]]>=100, Titanic[[#This Row],[Edad]] / 10, Titanic[[#This Row],[Edad]])) -> 22 | Q66: =IFERROR(LOOKUP(Titanic[[#This Row],[Edad Corrigida]],'Práctica 1'!$K$231:$K$240,'Práctica 1'!$L$231:$L$240), "DESCONOCIDO") -> 3. JOVEN | R66: =Titanic[[#This Row],[Familia Horizontal]]+Titanic[[#This Row],[Familia Vertical]] -> 0
B67: 62 | C67: 1 | D67: 1 | E67: Icard, Miss. Amelie | F67: Mujer | G67: 38 | H67: 0 | I67: 0 | J67: 80 | K67: 1 | M67: =IF(Titanic[[#This Row],[Sobrevive]]=1, "SOBREVIVE", "NO SOBREVIVE") -> SOBREVIVE | N67: =LOOKUP(Titanic[[#This Row],[Clase]],{1,2,3}, {"PRIMERA","SEGUNDA","TERCERA"}) -> PRIMERA | O67: =IF(Titanic[[#This Row],[Sexo]]="Hombre", "HOMBRE", "MUJER") -> MUJER | P67: =IF(Titanic[[#This Row],[Edad]]="", "", IF(Titanic[[#This Row],[Edad]]>=100, Titanic[[#This Row],[Edad]] / 10, Titanic[[#This Row],[Edad]])) -> 38 | Q67: =IFERROR(LOOKUP(Titanic[[#This Row],[Edad Corrigida]],'Práctica 1'!$K$231:$K$240,'Práctica 1'!$L$231:$L$240), "DESCONOCIDO") -> 7. ADULTO 2 | R67: =Titanic[[#This Row],[Familia Horizontal]]+Titanic[[#This Row],[Familia Vertical]] -> 0
B68: 63 | C68: 0 | D68: 1 | E68: Harris, Mr. Henry Birkhardt | F68: Hombre | G68: 45 | H68: 1 | I68: 0 | J68: 83475 | K68: 1 | L68: Southampton | M68: =IF(Titanic[[#This Row],[Sobrevive]]=1, "SOBREVIVE", "NO SOBREVIVE") -> NO SOBREVIVE | N68: =LOOKUP(Titanic[[#This Row],[Clase]],{1,2,3}, {"PRIMERA","SEGUNDA","TERCERA"}) -> PRIMERA | O68: =IF(Titanic[[#This Row],[Sexo]]="Hombre", "HOMBRE", "MUJER") -> HOMBRE | P68: =IF(Titanic[[#This Row],[Edad]]="", "", IF(Titanic[[#This Row],[Edad]]>=100, Titanic[[#This Row],[Edad]] / 10, Titanic[[#This Row],[Edad]])) -> 45 | Q68: =IFERROR(LOOKUP(Titanic[[#This Row],[Edad Corrigida]],'Práctica 1'!$K$231:$K$240,'Práctica 1'!$L$231:$L$240), "DESCONOCIDO") -> 8. ADULTO 3 | R68: =Titanic[[#This Row],[Familia Horizontal]]+Titanic[[#This Row],[Familia Vertical]] -> 1
B69: 64 | C69: 0 | D69: 3 | E69: Skoog, Master. Harald | F69: Hombre | G69: 4 | H69: 3 | I69: 2 | J69: 279 | K69: 0 | L69: Southampton | M69: =IF(Titanic[[#This Row],[Sobrevive]]=1, "SOBREVIVE", "NO SOBREVIVE") -> NO SOBREVIVE | N69: =LOOKUP(Titanic[[#This Row],[Clase]],{1,2,3}, {"PRIMERA","SEGUNDA","TERCERA"}) -> TERCERA | O69: =IF(Titanic[[#This Row],[Sexo]]="Hombre", "HOMBRE", "MUJER") -> HOMBRE | P69: =IF(Titanic[[#This Row],[Edad]]="", "", IF(Titanic[[#This Row],[Edad]]>=100, Titanic[[#This Row],[Edad]] / 10, Titanic[[#This Row],[Edad]])) -> 4 | Q69: =IFERROR(LOOKUP(Titanic[[#This Row],[Edad Corrigida]],'Práctica 1'!$K$231:$K$240,'Práctica 1'!$L$231:$L$240), "DESCONOCIDO") -> DESCONOCIDO | R69: =Titanic[[#This Row],[Familia Horizontal]]+Titanic[[#This Row],[Familia Vertical]] -> 5
B70: 65 | C70: 0 | D70: 1 | E70: Stewart, Mr. Albert A | F70: Hombre | H70: 0 | I70: 0 | J70: 277208 | K70: 0 | L70: Cherburg | M70: =IF(Titanic[[#This Row],[Sobrevive]]=1, "SOBREVIVE", "NO SOBREVIVE") -> NO SOBREVIVE | N70: =LOOKUP(Titanic[[#This Row],[Clase]],{1,2,3}, {"PRIMERA","SEGUNDA","TERCERA"}) -> PRIMERA | O70: =IF(Titanic[[#This Row],[Sexo]]="Hombre", "HOMBRE", "MUJER") -> HOMBRE | P70: =IF(Titanic[[#This Row],[Edad]]="", "", IF(Titanic[[#This Row],[Edad]]>=100, Titanic[[#This Row],[Edad]] / 10, Titanic[[#This Row],[Edad]])) | Q70: =IFERROR(LOOKUP(Titanic[[#This Row],[Edad Corrigida]],'Práctica 1'!$K$231:$K$240,'Práctica 1'!$L$231:$L$240), "DESCONOCIDO") -> DESCONOCIDO | R70: =Titanic[[#This Row],[Familia Horizontal]]+Titanic[[#This Row],[Familia Vertical]] -> 0
B71: 66 | C71: 1 | D71: 3 | E71: Moubarek, Master. Gerios | F71: Hombre | H71: 1 | I71: 1 | J71: 152458 | K71: 0 | L71: Cherburg | M71: =IF(Titanic[[#This Row],[Sobrevive]]=1, "SOBREVIVE", "NO SOBREVIVE") -> SOBREVIVE | N71: =LOOKUP(Titanic[[#This Row],[Clase]],{1,2,3}, {"PRIMERA","SEGUNDA","TERCERA"}) -> TERCERA | O71: =IF(Titanic[[#This Row],[Sexo]]="Hombre", "HOMBRE", "MUJER") -> HOMBRE | P71: =IF(Titanic[[#This Row],[Edad]]="", "", IF(Titanic[[#This Row],[Edad]]>=100, Titanic[[#This Row],[Edad]] / 10, Titanic[[#This Row],[Edad]])) | Q71: =IFERROR(LOOKUP(Titanic[[#This Row],[Edad Corrigida]],'Práctica 1'!$K$231:$K$240,'Práctica 1'!$L$231:$L$240), "DESCONOCIDO") -> DESCONOCIDO | R71: =Titanic[[#This Row],[Familia Horizontal]]+Titanic[[#This Row],[Familia Vertical]] -> 2
B72: 67 | C72: 1 | D72: 2 | E72: Nye, Mrs. (Elizabeth Ramell) | F72: Mujer | G72: 29 | H72: 0 | I72: 0 | J72: 105 | K72: 1 | L72: Southampton | M72: =IF(Titanic[[#This Row],[Sobrevive]]=1, "SOBREVIVE", "NO SOBREVIVE") -> SOBREVIVE | N72: =LOOKUP(Titanic[[#This Row],[Clase]],{1,2,3}, {"PRIMERA","SEGUNDA","TERCERA"}) -> SEGUNDA | O72: =IF(Titanic[[#This Row],[Sexo]]="Hombre", "HOMBRE", "MUJER") -> MUJER | P72: =IF(Titanic[[#This Row],[Edad]]="", "", IF(Titanic[[#This Row],[Edad]]>=100, Titanic[[#This Row],[Edad]] / 10, Titanic[[#This Row],[Edad]])) -> 29 | Q72: =IFERROR(LOOKUP(Titanic[[#This Row],[Edad Corrigida]],'Práctica 1'!$K$231:$K$240,'Práctica 1'!$L$231:$L$240), "DESCONOCIDO") -> 5. ADULTO | R72: =Titanic[[#This Row],[Familia Horizontal]]+Titanic[[#This Row],[Familia Vertical]] -> 0
B73: 68 | C73: 0 | D73: 3 | E73: Crease, Mr. Ernest James | F73: Hombre | G73: 19 | H73: 0 | I73: 0 | J73: 81583 | K73: 0 | L73: Southampton | M73: =IF(Titanic[[#This Row],[Sobrevive]]=1, "SOBREVIVE", "NO SOBREVIVE") -> NO SOBREVIVE | N73: =LOOKUP(Titanic[[#This Row],[Clase]],{1,2,3}, {"PRIMERA","SEGUNDA","TERCERA"}) -> TERCERA | O73: =IF(Titanic[[#This Row],[Sexo]]="Hombre", "HOMBRE", "MUJER") -> HOMBRE | P73: =IF(Titanic[[#This Row],[Edad]]="", "", IF(Titanic[[#This Row],[Edad]]>=100, Titanic[[#This Row],[Edad]] / 10, Titanic[[#This Row],[Edad]])) -> 19 | Q73: =IFERROR(LOOKUP(Titanic[[#This Row],[Edad Corrigida]],'Práctica 1'!$K$231:$K$240,'Práctica 1'!$L$231:$L$240), "DESCONOCIDO") -> 2. ADOLESCENTE | R73: =Titanic[[#This Row],[Familia Horizontal]]+Titanic[[#This Row],[Familia Vertical]] -> 0
B74: 69 | C74: 1 | D74: 3 | E74: Andersson, Miss. Erna Alexandra | F74: Mujer | G74: 17 | H74: 4 | I74: 2 | J74: 7925 | K74: 0 | L74: Southampton | M74: =IF(Titanic[[#This Row],[Sobrevive]]=1, "SOBREVIVE", "NO SOBREVIVE") -> SOBREVIVE | N74: =LOOKUP(Titanic[[#This Row],[Clase]],{1,2,3}, {"PRIMERA","SEGUNDA","TERCERA"}) -> TERCERA | O74: =IF(Titanic[[#This Row],[Sexo]]="Hombre", "HOMBRE", "MUJER") -> MUJER | P74: =IF(Titanic[[#This Row],[Edad]]="", "", IF(Titanic[[#This Row],[Edad]]>=100, Titanic[[#This Row],[Edad]] / 10, Titanic[[#This Row],[Edad]])) -> 17 | Q74: =IFERROR(LOOKUP(Titanic[[#This Row],[Edad Corrigida]],'Práctica 1'!$K$231:$K$240,'Práctica 1'!$L$231:$L$240), "DESCONOCIDO") -> 1. INFANTE | R74: =Titanic[[#This Row],[Familia Horizontal]]+Titanic[[#This Row],[Familia Vertical]] -> 6
B75: 70 | C75: 0 | D75: 3 | E75: Kink, Mr. Vincenz | F75: Hombre | G75: 26 | H75: 2 | I75: 0 | J75: 86625 | K75: 0 | L75: Southampton | M75: =IF(Titanic[[#This Row],[Sobrevive]]=1, "SOBREVIVE", "NO SOBREVIVE") -> NO SOBREVIVE | N75: =LOOKUP(Titanic[[#This Row],[Clase]],{1,2,3}, {"PRIMERA","SEGUNDA","TERCERA"}) -> TERCERA | O75: =IF(Titanic[[#This Row],[Sexo]]="Hombre", "HOMBRE", "MUJER") -> HOMBRE | P75: =IF(Titanic[[#This Row],[Edad]]="", "", IF(Titanic[[#This Row],[Edad]]>=100, Titanic[[#This Row],[Edad]] / 10, Titanic[[#This Row],[Edad]])) -> 26 | Q75: =IFERROR(LOOKUP(Titanic[[#This Row],[Edad Corrigida]],'Práctica 1'!$K$231:$K$240,'Práctica 1'!$L$231:$L$240), "DESCONOCIDO") -> 4. ADULTO JOVEN | R75: =Titanic[[#This Row],[Familia Horizontal]]+Titanic[[#This Row],[Familia Vertical]] -> 2
B76: 71 | C76: 0 | D76: 2 | E76: Jenkin, Mr. Stephen Curnow | F76: Hombre | G76: 32 | H76: 0 | I76: 0 | J76: 105 | K76: 0 | L76: Southampton | M76: =IF(Titanic[[#This Row],[Sobrevive]]=1, "SOBREVIVE", "NO SOBREVIVE") -> NO SOBREVIVE | N76: =LOOKUP(Titanic[[#This Row],[Clase]],{1,2,3}, {"PRIMERA","SEGUNDA","TERCERA"}) -> SEGUNDA | O76: =IF(Titanic[[#This Row],[Sexo]]="Hombre", "HOMBRE", "MUJER") -> HOMBRE | P76: =IF(Titanic[[#This Row],[Edad]]="", "", IF(Titanic[[#This Row],[Edad]]>=100, Titanic[[#This Row],[Edad]] / 10, Titanic[[#This Row],[Edad]])) -> 32 | Q76: =IFERROR(LOOKUP(Titanic[[#This Row],[Edad Corrigida]],'Práctica 1'!$K$231:$K$240,'Práctica 1'!$L$231:$L$240), "DESCONOCIDO") -> 6. ADULTO 1 | R76: =Titanic[[#This Row],[Familia Horizontal]]+Titanic[[#This Row],[Familia Vertical]] -> 0
B77: 72 | C77: 0 | D77: 3 | E77: Goodwin, Miss. Lillian Amy | F77: Mujer | G77: 16 | H77: 5 | I77: 2 | J77: 469 | K77: 0 | L77: Southampton | M77: =IF(Titanic[[#This Row],[Sobrevive]]=1, "SOBREVIVE", "NO SOBREVIVE") -> NO SOBREVIVE | N77: =LOOKUP(Titanic[[#This Row],[Clase]],{1,2,3}, {"PRIMERA","SEGUNDA","TERCERA"}) -> TERCERA | O77: =IF(Titanic[[#This Row],[Sexo]]="Hombre", "HOMBRE", "MUJER") -> MUJER | P77: =IF(Titanic[[#This Row],[Edad]]="", "", IF(Titanic[[#This Row],[Edad]]>=100, Titanic[[#This Row],[Edad]] / 10, Titanic[[#This Row],[Edad]])) -> 16 | Q77: =IFERROR(LOOKUP(Titanic[[#This Row],[Edad Corrigida]],'Práctica 1'!$K$231:$K$240,'Práctica 1'!$L$231:$L$240), "DESCONOCIDO") -> 1. INFANTE | R77: =Titanic[[#This Row],[Familia Horizontal]]+Titanic[[#This Row],[Familia Vertical]] -> 7
B78: 73 | C78: 0 | D78: 2 | E78: Hood, Mr. Ambrose Jr | F78: Hombre | G78: 21 | H78: 0 | I78: 0 | J78: 735 | K78: 0 | L78: Southampton | M78: =IF(Titanic[[#This Row],[Sobrevive]]=1, "SOBREVIVE", "NO SOBREVIVE") -> NO SOBREVIVE | N78: =LOOKUP(Titanic[[#This Row],[Clase]],{1,2,3}, {"PRIMERA","SEGUNDA","TERCERA"}) -> SEGUNDA | O78: =IF(Titanic[[#This Row],[Sexo]]="Hombre", "HOMBRE", "MUJER") -> HOMBRE | P78: =IF(Titanic[[#This Row],[Edad]]="", "", IF(Titanic[[#This Row],[Edad]]>=100, Titanic[[#This Row],[Edad]] / 10, Titanic[[#This Row],[Edad]])) -> 21 | Q78: =IFERROR(LOOKUP(Titanic[[#This Row],[Edad Corrigida]],'Práctica 1'!$K$231:$K$240,'Práctica 1'!$L$231:$L$240), "DESCONOCIDO") -> 2. ADOLESCENTE | R78: =Titanic[[#This Row],[Familia Horizontal]]+Titanic[[#This Row],[Familia Vertical]] -> 0
B79: 74 | C79: 0 | D79: 3 | E79: Chronopoulos, Mr. Apostolos | F79: Hombre | G79: 26 | H79: 1 | I79: 0 | J79: 144542 | K79: 0 | L79: Cherburg | M79: =IF(Titanic[[#This Row],[Sobrevive]]=1, "SOBREVIVE", "NO SOBREVIVE") -> NO SOBREVIVE | N79: =LOOKUP(Titanic[[#This Row],[Clase]],{1,2,3}, {"PRIMERA","SEGUNDA","TERCERA"}) -> TERCERA | O79: =IF(Titanic[[#This Row],[Sexo]]="Hombre", "HOMBRE", "MUJER") -> HOMBRE | P79: =IF(Titanic[[#This Row],[Edad]]="", "", IF(Titanic[[#This Row],[Edad]]>=100, Titanic[[#This Row],[Edad]] / 10, Titanic[[#This Row],[Edad]])) -> 26 | Q79: =IFERROR(LOOKUP(Titanic[[#This Row],[Edad Corrigida]],'Práctica 1'!$K$231:$K$240,'Práctica 1'!$L$231:$L$240), "DESCONOCIDO") -> 4. ADULTO JOVEN | R79: =Titanic[[#This Row],[Familia Horizontal]]+Titanic[[#This Row],[Familia Vertical]] -> 1
B80: 75 | C80: 1 | D80: 3 | E80: Bing, Mr. Lee | F80: Hombre | G80: 32 | H80: 0 | I80: 0 | J80: 564958 | K80: 0 | L80: Southampton | M80: =IF(Titanic[[#This Row],[Sobrevive]]=1, "SOBREVIVE", "NO SOBREVIVE") -> SOBREVIVE | N80: =LOOKUP(Titanic[[#This Row],[Clase]],{1,2,3}, {"PRIMERA","SEGUNDA","TERCERA"}) -> TERCERA | O80: =IF(Titanic[[#This Row],[Sexo]]="Hombre", "HOMBRE", "MUJER") -> HOMBRE | P80: =IF(Titanic[[#This Row],[Edad]]="", "", IF(Titanic[[#This Row],[Edad]]>=100, Titanic[[#This Row],[Edad]] / 10, Titanic[[#This Row],[Edad]])) -> 32 | Q80: =IFERROR(LOOKUP(Titanic[[#This Row],[Edad Corrigida]],'Práctica 1'!$K$231:$K$240,'Práctica 1'!$L$231:$L$240), "DESCONOCIDO") -> 6. ADULTO 1 | R80: =Titanic[[#This Row],[Familia Horizontal]]+Titanic[[#This Row],[Familia Vertical]] -> 0
B81: 76 | C81: 0 | D81: 3 | E81: Moen, Mr. Sigurd Hansen | F81: Hombre | G81: 25 | H81: 0 | I81: 0 | J81: 765 | K81: 1 | L81: Southampton | M81: =IF(Titanic[[#This Row],[Sobrevive]]=1, "SOBREVIVE", "NO SOBREVIVE") -> NO SOBREVIVE | N81: =LOOKUP(Titanic[[#This Row],[Clase]],{1,2,3}, {"PRIMERA","SEGUNDA","TERCERA"}) -> TERCERA | O81: =IF(Titanic[[#This Row],[Sexo]]="Hombre", "HOMBRE", "MUJER") -> HOMBRE | P81: =IF(Titanic[[#This Row],[Edad]]="", "", IF(Titanic[[#This Row],[Edad]]>=100, Titanic[[#This Row],[Edad]] / 10, Titanic[[#This Row],[Edad]])) -> 25 | Q81: =IFERROR(LOOKUP(Titanic[[#This Row],[Edad Corrigida]],'Práctica 1'!$K$231:$K$240,'Práctica 1'!$L$231:$L$240), "DESCONOCIDO") -> 4. ADULTO JOVEN | R81: =Titanic[[#This Row],[Familia Horizontal]]+Titanic[[#This Row],[Familia Vertical]] -> 0
B82: 77 | C82: 0 | D82: 3 | E82: Staneff, Mr. Ivan | F82: Hombre | H82: 0 | I82: 0 | J82: 78958 | K82: 0 | L82: Southampton | M82: =IF(Titanic[[#This Row],[Sobrevive]]=1, "SOBREVIVE", "NO SOBREVIVE") -> NO SOBREVIVE | N82: =LOOKUP(Titanic[[#This Row],[Clase]],{1,2,3}, {"PRIMERA","SEGUNDA","TERCERA"}) -> TERCERA | O82: =IF(Titanic[[#This Row],[Sexo]]="Hombre", "HOMBRE", "MUJER") -> HOMBRE | P82: =IF(Titanic[[#This Row],[Edad]]="", "", IF(Titanic[[#This Row],[Edad]]>=100, Titanic[[#This Row],[Edad]] / 10, Titanic[[#This Row],[Edad]])) | Q82: =IFERROR(LOOKUP(Titanic[[#This Row],[Edad Corrigida]],'Práctica 1'!$K$231:$K$240,'Práctica 1'!$L$231:$L$240), "DESCONOCIDO") -> DESCONOCIDO | R82: =Titanic[[#This Row],[Familia Horizontal]]+Titanic[[#This Row],[Familia Vertical]] -> 0
B83: 78 | C83: 0 | D83: 3 | E83: Moutal, Mr. Rahamin Haim | F83: Hombre | H83: 0 | I83: 0 | J83: 805 | K83: 0 | L83: Southampton | M83: =IF(Titanic[[#This Row],[Sobrevive]]=1, "SOBREVIVE", "NO SOBREVIVE") -> NO SOBREVIVE | N83: =LOOKUP(Titanic[[#This Row],[Clase]],{1,2,3}, {"PRIMERA","SEGUNDA","TERCERA"}) -> TERCERA | O83: =IF(Titanic[[#This Row],[Sexo]]="Hombre", "HOMBRE", "MUJER") -> HOMBRE | P83: =IF(Titanic[[#This Row],[Edad]]="", "", IF(Titanic[[#This Row],[Edad]]>=100, Titanic[[#This Row],[Edad]] / 10, Titanic[[#This Row],[Edad]])) | Q83: =IFERROR(LOOKUP(Titanic[[#This Row],[Edad Corrigida]],'Práctica 1'!$K$231:$K$240,'Práctica 1'!$L$231:$L$240), "DESCONOCIDO") -> DESCONOCIDO | R83: =Titanic[[#This Row],[Familia Horizontal]]+Titanic[[#This Row],[Familia Vertical]] -> 0
B84: 79 | C84: 1 | D84: 2 | E84: Caldwell, Master. Alden Gates | F84: Hombre | G84: 83 | H84: 0 | I84: 2 | J84: 29 | K84: 0 | L84: Southampton | M84: =IF(Titanic[[#This Row],[Sobrevive]]=1, "SOBREVIVE", "NO SOBREVIVE") -> SOBREVIVE | N84: =LOOKUP(Titanic[[#This Row],[Clase]],{1,2,3}, {"PRIMERA","SEGUNDA","TERCERA"}) -> SEGUNDA | O84: =IF(Titanic[[#This Row],[Sexo]]="Hombre", "HOMBRE", "MUJER") -> HOMBRE | P84: =IF(Titanic[[#This Row],[Edad]]="", "", IF(Titanic[[#This Row],[Edad]]>=100, Titanic[[#This Row],[Edad]] / 10, Titanic[[#This Row],[Edad]])) -> 83 | Q84: =IFERROR(LOOKUP(Titanic[[#This Row],[Edad Corrigida]],'Práctica 1'!$K$231:$K$240,'Práctica 1'!$L$231:$L$240), "DESCONOCIDO") -> 9. ADULTO 4 | R84: =Titanic[[#This Row],[Familia Horizontal]]+Titanic[[#This Row],[Familia Vertical]] -> 2
B85: 80 | C85: 1 | D85: 3 | E85: Dowdell, Miss. Elizabeth | F85: Mujer | G85: 30 | H85: 0 | I85: 0 | J85: 12475 | K85: 0 | L85: Southampton | M85: =IF(Titanic[[#This Row],[Sobrevive]]=1, "SOBREVIVE", "NO SOBREVIVE") -> SOBREVIVE | N85: =LOOKUP(Titanic[[#This Row],[Clase]],{1,2,3}, {"PRIMERA","SEGUNDA","TERCERA"}) -> TERCERA | O85: =IF(Titanic[[#This Row],[Sexo]]="Hombre", "HOMBRE", "MUJER") -> MUJER | P85: =IF(Titanic[[#This Row],[Edad]]="", "", IF(Titanic[[#This Row],[Edad]]>=100, Titanic[[#This Row],[Edad]] / 10, Titanic[[#This Row],[Edad]])) -> 30 | Q85: =IFERROR(LOOKUP(Titanic[[#This Row],[Edad Corrigida]],'Práctica 1'!$K$231:$K$240,'Práctica 1'!$L$231:$L$240), "DESCONOCIDO") -> 5. ADULTO | R85: =Titanic[[#This Row],[Familia Horizontal]]+Titanic[[#This Row],[Familia Vertical]] -> 0
B86: 81 | C86: 0 | D86: 3 | E86: Waelens, Mr. Achille | F86: Hombre | G86: 22 | H86: 0 | I86: 0 | J86: 9 | K86: 0 | L86: Southampton | M86: =IF(Titanic[[#This Row],[Sobrevive]]=1, "SOBREVIVE", "NO SOBREVIVE") -> NO SOBREVIVE | N86: =LOOKUP(Titanic[[#This Row],[Clase]],{1,2,3}, {"PRIMERA","SEGUNDA","TERCERA"}) -> TERCERA | O86: =IF(Titanic[[#This Row],[Sexo]]="Hombre", "HOMBRE", "MUJER") -> HOMBRE | P86: =IF(Titanic[[#This Row],[Edad]]="", "", IF(Titanic[[#This Row],[Edad]]>=100, Titanic[[#This Row],[Edad]] / 10, Titanic[[#This Row],[Edad]])) -> 22 | Q86: =IFERROR(LOOKUP(Titanic[[#This Row],[Edad Corrigida]],'Práctica 1'!$K$231:$K$240,'Práctica 1'!$L$231:$L$240), "DESCONOCIDO") -> 3. JOVEN | R86: =Titanic[[#This Row],[Familia Horizontal]]+Titanic[[#This Row],[Familia Vertical]] -> 0
B87: 82 | C87: 1 | D87: 3 | E87: Sheerlinck, Mr. Jan Baptist | F87: Hombre | G87: 29 | H87: 0 | I87: 0 | J87: 95 | K87: 0 | L87: Southampton | M87: =IF(Titanic[[#This Row],[Sobrevive]]=1, "SOBREVIVE", "NO SOBREVIVE") -> SOBREVIVE | N87: =LOOKUP(Titanic[[#This Row],[Clase]],{1,2,3}, {"PRIMERA","SEGUNDA","TERCERA"}) -> TERCERA | O87: =IF(Titanic[[#This Row],[Sexo]]="Hombre", "HOMBRE", "MUJER") -> HOMBRE | P87: =IF(Titanic[[#This Row],[Edad]]="", "", IF(Titanic[[#This Row],[Edad]]>=100, Titanic[[#This Row],[Edad]] / 10, Titanic[[#This Row],[Edad]])) -> 29 | Q87: =IFERROR(LOOKUP(Titanic[[#This Row],[Edad Corrigida]],'Práctica 1'!$K$231:$K$240,'Práctica 1'!$L$231:$L$240), "DESCONOCIDO") -> 5. ADULTO | R87: =Titanic[[#This Row],[Familia Horizontal]]+Titanic[[#This Row],[Familia Vertical]] -> 0
B88: 83 | C88: 1 | D88: 3 | E88: McDermott, Miss. Brigdet Delia | F88: Mujer | H88: 0 | I88: 0 | J88: 77875 | K88: 0 | L88: Queenstown | M88: =IF(Titanic[[#This Row],[Sobrevive]]=1, "SOBREVIVE", "NO SOBREVIVE") -> SOBREVIVE | N88: =LOOKUP(Titanic[[#This Row],[Clase]],{1,2,3}, {"PRIMERA","SEGUNDA","TERCERA"}) -> TERCERA | O88: =IF(Titanic[[#This Row],[Sexo]]="Hombre", "HOMBRE", "MUJER") -> MUJER | P88: =IF(Titanic[[#This Row],[Edad]]="", "", IF(Titanic[[#This Row],[Edad]]>=100, Titanic[[#This Row],[Edad]] / 10, Titanic[[#This Row],[Edad]])) | Q88: =IFERROR(LOOKUP(Titanic[[#This Row],[Edad Corrigida]],'Práctica 1'!$K$231:$K$240,'Práctica 1'!$L$231:$L$240), "DESCONOCIDO") -> DESCONOCIDO | R88: =Titanic[[#This Row],[Familia Horizontal]]+Titanic[[#This Row],[Familia Vertical]] -> 0
B89: 84 | C89: 0 | D89: 1 | E89: Carrau, Mr. Francisco M | F89: Hombre | G89: 28 | H89: 0 | I89: 0 | J89: 471 | K89: 0 | L89: Southampton | M89: =IF(Titanic[[#This Row],[Sobrevive]]=1, "SOBREVIVE", "NO SOBREVIVE") -> NO SOBREVIVE | N89: =LOOKUP(Titanic[[#This Row],[Clase]],{1,2,3}, {"PRIMERA","SEGUNDA","TERCERA"}) -> PRIMERA | O89: =IF(Titanic[[#This Row],[Sexo]]="Hombre", "HOMBRE", "MUJER") -> HOMBRE | P89: =IF(Titanic[[#This Row],[Edad]]="", "", IF(Titanic[[#This Row],[Edad]]>=100, Titanic[[#This Row],[Edad]] / 10, Titanic[[#This Row],[Edad]])) -> 28 | Q89: =IFERROR(LOOKUP(Titanic[[#This Row],[Edad Corrigida]],'Práctica 1'!$K$231:$K$240,'Práctica 1'!$L$231:$L$240), "DESCONOCIDO") -> 4. ADULTO JOVEN | R89: =Titanic[[#This Row],[Familia Horizontal]]+Titanic[[#This Row],[Familia Vertical]] -> 0
B90: 85 | C90: 1 | D90: 2 | E90: Ilett, Miss. Bertha | F90: Mujer | G90: 17 | H90: 0 | I90: 0 | J90: 105 | K90: 0 | L90: Southampton | M90: =IF(Titanic[[#This Row],[Sobrevive]]=1, "SOBREVIVE", "NO SOBREVIVE") -> SOBREVIVE | N90: =LOOKUP(Titanic[[#This Row],[Clase]],{1,2,3}, {"PRIMERA","SEGUNDA","TERCERA"}) -> SEGUNDA | O90: =IF(Titanic[[#This Row],[Sexo]]="Hombre", "HOMBRE", "MUJER") -> MUJER | P90: =IF(Titanic[[#This Row],[Edad]]="", "", IF(Titanic[[#This Row],[Edad]]>=100, Titanic[[#This Row],[Edad]] / 10, Titanic[[#This Row],[Edad]])) -> 17 | Q90: =IFERROR(LOOKUP(Titanic[[#This Row],[Edad Corrigida]],'Práctica 1'!$K$231:$K$240,'Práctica 1'!$L$231:$L$240), "DESCONOCIDO") -> 1. INFANTE | R90: =Titanic[[#This Row],[Familia Horizontal]]+Titanic[[#This Row],[Familia Vertical]] -> 0
B91: 86 | C91: 1 | D91: 3 | E91: Backstrom, Mrs. Karl Alfred (Maria Mathilda Gustafsson) | F91: Mujer | G91: 33 | H91: 3 | I91: 0 | J91: 1585 | K91: 0 | L91: Southampton | M91: =IF(Titanic[[#This Row],[Sobrevive]]=1, "SOBREVIVE", "NO SOBREVIVE") -> SOBREVIVE | N91: =LOOKUP(Titanic[[#This Row],[Clase]],{1,2,3}, {"PRIMERA","SEGUNDA","TERCERA"}) -> TERCERA | O91: =IF(Titanic[[#This Row],[Sexo]]="Hombre", "HOMBRE", "MUJER") -> MUJER | P91: =IF(Titanic[[#This Row],[Edad]]="", "", IF(Titanic[[#This Row],[Edad]]>=100, Titanic[[#This Row],[Edad]] / 10, Titanic[[#This Row],[Edad]])) -> 33 | Q91: =IFERROR(LOOKUP(Titanic[[#This Row],[Edad Corrigida]],'Práctica 1'!$K$231:$K$240,'Práctica 1'!$L$231:$L$240), "DESCONOCIDO") -> 6. ADULTO 1 | R91: =Titanic[[#This Row],[Familia Horizontal]]+Titanic[[#This Row],[Familia Vertical]] -> 3
B92: 87 | C92: 0 | D92: 3 | E92: Ford, Mr. William Neal | F92: Hombre | G92: 16 | H92: 1 | I92: 3 | J92: 34375 | K92: 0 | L92: Southampton | M92: =IF(Titanic[[#This Row],[Sobrevive]]=1, "SOBREVIVE", "NO SOBREVIVE") -> NO SOBREVIVE | N92: =LOOKUP(Titanic[[#This Row],[Clase]],{1,2,3}, {"PRIMERA","SEGUNDA","TERCERA"}) -> TERCERA | O92: =IF(Titanic[[#This Row],[Sexo]]="Hombre", "HOMBRE", "MUJER") -> HOMBRE | P92: =IF(Titanic[[#This Row],[Edad]]="", "", IF(Titanic[[#This Row],[Edad]]>=100, Titanic[[#This Row],[Edad]] / 10, Titanic[[#This Row],[Edad]])) -> 16 | Q92: =IFERROR(LOOKUP(Titanic[[#This Row],[Edad Corrigida]],'Práctica 1'!$K$231:$K$240,'Práctica 1'!$L$231:$L$240), "DESCONOCIDO") -> 1. INFANTE | R92: =Titanic[[#This Row],[Familia Horizontal]]+Titanic[[#This Row],[Familia Vertical]] -> 4
B93: 88 | C93: 0 | D93: 3 | E93: Slocovski, Mr. Selman Francis | F93: Hombre | H93: 0 | I93: 0 | J93: 805 | K93: 0 | L93: Southampton | M93: =IF(Titanic[[#This Row],[Sobrevive]]=1, "SOBREVIVE", "NO SOBREVIVE") -> NO SOBREVIVE | N93: =LOOKUP(Titanic[[#This Row],[Clase]],{1,2,3}, {"PRIMERA","SEGUNDA","TERCERA"}) -> TERCERA | O93: =IF(Titanic[[#This Row],[Sexo]]="Hombre", "HOMBRE", "MUJER") -> HOMBRE | P93: =IF(Titanic[[#This Row],[Edad]]="", "", IF(Titanic[[#This Row],[Edad]]>=100, Titanic[[#This Row],[Edad]] / 10, Titanic[[#This Row],[Edad]])) | Q93: =IFERROR(LOOKUP(Titanic[[#This Row],[Edad Corrigida]],'Práctica 1'!$K$231:$K$240,'Práctica 1'!$L$231:$L$240), "DESCONOCIDO") -> DESCONOCIDO | R93: =Titanic[[#This Row],[Familia Horizontal]]+Titanic[[#This Row],[Familia Vertical]] -> 0
B94: 89 | C94: 1 | D94: 1 | E94: Fortune, Miss. Mabel Helen | F94: Mujer | G94: 23 | H94: 3 | I94: 2 | J94: 263 | K94: 1 | L94: Southampton | M94: =IF(Titanic[[#This Row],[Sobrevive]]=1, "SOBREVIVE", "NO SOBREVIVE") -> SOBREVIVE | N94: =LOOKUP(Titanic[[#This Row],[Clase]],{1,2,3}, {"PRIMERA","SEGUNDA","TERCERA"}) -> PRIMERA | O94: =IF(Titanic[[#This Row],[Sexo]]="Hombre", "HOMBRE", "MUJER") -> MUJER | P94: =IF(Titanic[[#This Row],[Edad]]="", "", IF(Titanic[[#This Row],[Edad]]>=100, Titanic[[#This Row],[Edad]] / 10, Titanic[[#This Row],[Edad]])) -> 23 | Q94: =IFERROR(LOOKUP(Titanic[[#This Row],[Edad Corrigida]],'Práctica 1'!$K$231:$K$240,'Práctica 1'!$L$231:$L$240), "DESCONOCIDO") -> 3. JOVEN | R94: =Titanic[[#This Row],[Familia Horizontal]]+Titanic[[#This Row],[Familia Vertical]] -> 5
B95: 90 | C95: 0 | D95: 3 | E95: Celotti, Mr. Francesco | F95: Hombre | G95: 24 | H95: 0 | I95: 0 | J95: 805 | K95: 0 | L95: Southampton | M95: =IF(Titanic[[#This Row],[Sobrevive]]=1, "SOBREVIVE", "NO SOBREVIVE") -> NO SOBREVIVE | N95: =LOOKUP(Titanic[[#This Row],[Clase]],{1,2,3}, {"PRIMERA","SEGUNDA","TERCERA"}) -> TERCERA | O95: =IF(Titanic[[#This Row],[Sexo]]="Hombre", "HOMBRE", "MUJER") -> HOMBRE | P95: =IF(Titanic[[#This Row],[Edad]]="", "", IF(Titanic[[#This Row],[Edad]]>=100, Titanic[[#This Row],[Edad]] / 10, Titanic[[#This Row],[Edad]])) -> 24 | Q95: =IFERROR(LOOKUP(Titanic[[#This Row],[Edad Corrigida]],'Práctica 1'!$K$231:$K$240,'Práctica 1'!$L$231:$L$240), "DESCONOCIDO") -> 3. JOVEN | R95: =Titanic[[#This Row],[Familia Horizontal]]+Titanic[[#This Row],[Familia Vertical]] -> 0
B96: 91 | C96: 0 | D96: 3 | E96: Christmann, Mr. Emil | F96: Hombre | G96: 29 | H96: 0 | I96: 0 | J96: 805 | K96: 0 | L96: Southampton | M96: =IF(Titanic[[#This Row],[Sobrevive]]=1, "SOBREVIVE", "NO SOBREVIVE") -> NO SOBREVIVE | N96: =LOOKUP(Titanic[[#This Row],[Clase]],{1,2,3}, {"PRIMERA","SEGUNDA","TERCERA"}) -> TERCERA | O96: =IF(Titanic[[#This Row],[Sexo]]="Hombre", "HOMBRE", "MUJER") -> HOMBRE | P96: =IF(Titanic[[#This Row],[Edad]]="", "", IF(Titanic[[#This Row],[Edad]]>=100, Titanic[[#This Row],[Edad]] / 10, Titanic[[#This Row],[Edad]])) -> 29 | Q96: =IFERROR(LOOKUP(Titanic[[#This Row],[Edad Corrigida]],'Práctica 1'!$K$231:$K$240,'Práctica 1'!$L$231:$L$240), "DESCONOCIDO") -> 5. ADULTO | R96: =Titanic[[#This Row],[Familia Horizontal]]+Titanic[[#This Row],[Familia Vertical]] -> 0
B97: 92 | C97: 0 | D97: 3 | E97: Andreasson, Mr. Paul Edvin | F97: Hombre | G97: 20 | H97: 0 | I97: 0 | J97: 78542 | K97: 0 | L97: Southampton | M97: =IF(Titanic[[#This Row],[Sobrevive]]=1, "SOBREVIVE", "NO SOBREVIVE") -> NO SOBREVIVE | N97: =LOOKUP(Titanic[[#This Row],[Clase]],{1,2,3}, {"PRIMERA","SEGUNDA","TERCERA"}) -> TERCERA | O97: =IF(Titanic[[#This Row],[Sexo]]="Hombre", "HOMBRE", "MUJER") -> HOMBRE | P97: =IF(Titanic[[#This Row],[Edad]]="", "", IF(Titanic[[#This Row],[Edad]]>=100, Titanic[[#This Row],[Edad]] / 10, Titanic[[#This Row],[Edad]])) -> 20 | Q97: =IFERROR(LOOKUP(Titanic[[#This Row],[Edad Corrigida]],'Práctica 1'!$K$231:$K$240,'Práctica 1'!$L$231:$L$240), "DESCONOCIDO") -> 2. ADOLESCENTE | R97: =Titanic[[#This Row],[Familia Horizontal]]+Titanic[[#This Row],[Familia Vertical]] -> 0
B98: 93 | C98: 0 | D98: 1 | E98: Chaffee, Mr. Herbert Fuller | F98: Hombre | G98: 46 | H98: 1 | I98: 0 | J98: 61175 | K98: 1 | L98: Southampton | M98: =IF(Titanic[[#This Row],[Sobrevive]]=1, "SOBREVIVE", "NO SOBREVIVE") -> NO SOBREVIVE | N98: =LOOKUP(Titanic[[#This Row],[Clase]],{1,2,3}, {"PRIMERA","SEGUNDA","TERCERA"}) -> PRIMERA | O98: =IF(Titanic[[#This Row],[Sexo]]="Hombre", "HOMBRE", "MUJER") -> HOMBRE | P98: =IF(Titanic[[#This Row],[Edad]]="", "", IF(Titanic[[#This Row],[Edad]]>=100, Titanic[[#This Row],[Edad]] / 10, Titanic[[#This Row],[Edad]])) -> 46 | Q98: =IFERROR(LOOKUP(Titanic[[#This Row],[Edad Corrigida]],'Práctica 1'!$K$231:$K$240,'Práctica 1'!$L$231:$L$240), "DESCONOCIDO") -> 8. ADULTO 3 | R98: =Titanic[[#This Row],[Familia Horizontal]]+Titanic[[#This Row],[Familia Vertical]] -> 1
B99: 94 | C99: 0 | D99: 3 | E99: Dean, Mr. Bertram Frank | F99: Hombre | G99: 26 | H99: 1 | I99: 2 | J99: 20575 | K99: 0 | L99: Southampton | M99: =IF(Titanic[[#This Row],[Sobrevive]]=1, "SOBREVIVE", "NO SOBREVIVE") -> NO SOBREVIVE | N99: =LOOKUP(Titanic[[#This Row],[Clase]],{1,2,3}, {"PRIMERA","SEGUNDA","TERCERA"}) -> TERCERA | O99: =IF(Titanic[[#This Row],[Sexo]]="Hombre", "HOMBRE", "MUJER") -> HOMBRE | P99: =IF(Titanic[[#This Row],[Edad]]="", "", IF(Titanic[[#This Row],[Edad]]>=100, Titanic[[#This Row],[Edad]] / 10, Titanic[[#This Row],[Edad]])) -> 26 | Q99: =IFERROR(LOOKUP(Titanic[[#This Row],[Edad Corrigida]],'Práctica 1'!$K$231:$K$240,'Práctica 1'!$L$231:$L$240), "DESCONOCIDO") -> 4. ADULTO JOVEN | R99: =Titanic[[#This Row],[Familia Horizontal]]+Titanic[[#This Row],[Familia Vertical]] -> 3
B100: 95 | C100: 0 | D100: 3 | E100: Coxon, Mr. Daniel | F100: Hombre | G100: 59 | H100: 0 | I100: 0 | J100: 725 | K100: 0 | L100: Southampton | M100: =IF(Titanic[[#This Row],[Sobrevive]]=1, "SOBREVIVE", "NO SOBREVIVE") -> NO SOBREVIVE | N100: =LOOKUP(Titanic[[#This Row],[Clase]],{1,2,3}, {"PRIMERA","SEGUNDA","TERCERA"}) -> TERCERA | O100: =IF(Titanic[[#This Row],[Sexo]]="Hombre", "HOMBRE", "MUJER") -> HOMBRE | P100: =IF(Titanic[[#This Row],[Edad]]="", "", IF(Titanic[[#This Row],[Edad]]>=100, Titanic[[#This Row],[Edad]] / 10, Titanic[[#This Row],[Edad]])) -> 59 | Q100: =IFERROR(LOOKUP(Titanic[[#This Row],[Edad Corrigida]],'Práctica 1'!$K$231:$K$240,'Práctica 1'!$L$231:$L$240), "DESCONOCIDO") -> 9. ADULTO 4 | R100: =Titanic[[#This Row],[Familia Horizontal]]+Titanic[[#This Row],[Familia Vertical]] -> 0
B101: 96 | C101: 0 | D101: 3 | E101: Shorney, Mr. Charles Joseph | F101: Hombre | H101: 0 | I101: 0 | J101: 805 | K101: 0 | L101: Southampton | M101: =IF(Titanic[[#This Row],[Sobrevive]]=1, "SOBREVIVE", "NO SOBREVIVE") -> NO SOBREVIVE | N101: =LOOKUP(Titanic[[#This Row],[Clase]],{1,2,3}, {"PRIMERA","SEGUNDA","TERCERA"}) -> TERCERA | O101: =IF(Titanic[[#This Row],[Sexo]]="Hombre", "HOMBRE", "MUJER") -> HOMBRE | P101: =IF(Titanic[[#This Row],[Edad]]="", "", IF(Titanic[[#This Row],[Edad]]>=100, Titanic[[#This Row],[Edad]] / 10, Titanic[[#This Row],[Edad]])) | Q101: =IFERROR(LOOKUP(Titanic[[#This Row],[Edad Corrigida]],'Práctica 1'!$K$231:$K$240,'Práctica 1'!$L$231:$L$240), "DESCONOCIDO") -> DESCONOCIDO | R101: =Titanic[[#This Row],[Familia Horizontal]]+Titanic[[#This Row],[Familia Vertical]] -> 0
B102: 97 | C102: 0 | D102: 1 | E102: Goldschmidt, Mr. George B | F102: Hombre | G102: 71 | H102: 0 | I102: 0 | J102: 346542 | K102: 1 | L102: Cherburg | M102: =IF(Titanic[[#This Row],[Sobrevive]]=1, "SOBREVIVE", "NO SOBREVIVE") -> NO SOBREVIVE | N102: =LOOKUP(Titanic[[#This Row],[Clase]],{1,2,3}, {"PRIMERA","SEGUNDA","TERCERA"}) -> PRIMERA | O102: =IF(Titanic[[#This Row],[Sexo]]="Hombre", "HOMBRE", "MUJER") -> HOMBRE | P102: =IF(Titanic[[#This Row],[Edad]]="", "", IF(Titanic[[#This Row],[Edad]]>=100, Titanic[[#This Row],[Edad]] / 10, Titanic[[#This Row],[Edad]])) -> 71 | Q102: =IFERROR(LOOKUP(Titanic[[#This Row],[Edad Corrigida]],'Práctica 1'!$K$231:$K$240,'Práctica 1'!$L$231:$L$240), "DESCONOCIDO") -> 9. ADULTO 4 | R102: =Titanic[[#This Row],[Familia Horizontal]]+Titanic[[#This Row],[Familia Vertical]] -> 0
B103: 98 | C103: 1 | D103: 1 | E103: Greenfield, Mr. William Bertram | F103: Hombre | G103: 23 | H103: 0 | I103: 1 | J103: 633583 | K103: 1 | L103: Cherburg | M103: =IF(Titanic[[#This Row],[Sobrevive]]=1, "SOBREVIVE", "NO SOBREVIVE") -> SOBREVIVE | N103: =LOOKUP(Titanic[[#This Row],[Clase]],{1,2,3}, {"PRIMERA","SEGUNDA","TERCERA"}) -> PRIMERA | O103: =IF(Titanic[[#This Row],[Sexo]]="Hombre", "HOMBRE", "MUJER") -> HOMBRE | P103: =IF(Titanic[[#This Row],[Edad]]="", "", IF(Titanic[[#This Row],[Edad]]>=100, Titanic[[#This Row],[Edad]] / 10, Titanic[[#This Row],[Edad]])) -> 23 | Q103: =IFERROR(LOOKUP(Titanic[[#This Row],[Edad Corrigida]],'Práctica 1'!$K$231:$K$240,'Práctica 1'!$L$231:$L$240), "DESCONOCIDO") -> 3. JOVEN | R103: =Titanic[[#This Row],[Familia Horizontal]]+Titanic[[#This Row],[Familia Vertical]] -> 1
...

Sheet Análisis de Edades por Deciles
B3: Cuenta de C Sobrevive | C3: Etiquetas de columna
B4: Etiquetas de fila | C4: NO SOBREVIVE | D4: SOBREVIVE | E4: Total general
B5: 1. INFANTE | C5: 1 | D5: 10 | E5: 11
B6: 2. ADOLESCENTE | C6: 3 | D6: 5 | E6: 8
B7: 3. JOVEN | C7: 3 | D7: 12 | E7: 15
B8: 4. ADULTO JOVEN | C8: 4 | D8: 9 | E8: 13
B9: 5. ADULTO | C9: 5 | D9: 9 | E9: 14
B10: 6. ADULTO 1 | C10: 1 | D10: 15 | E10: 16
B11: 7. ADULTO 2 | C11: 9 | D11: 20 | E11: 29
B12: 8. ADULTO 3 | C12: 13 | D12: 18 | E12: 31
B13: 9. ADULTO 4 | C13: 24 | D13: 20 | E13: 44
B14: A. ADULTO MAYOR | D14: 1 | E14: 1
B15: Total general | C15: 63 | D15: 119 | E15: 182
M33: Informe
M35: Para hombres
M37: La supervivencia aumenta ligeramente cuando la edad pertence a Adulto 1 (cerca de los 32 años) y Adulto 3 (cerca de los 42 años)
M40: Para mujeres
M42: …

Sheet Hoja8
D2: Cortes de Familiares | G2: Cortes de Pagado
B3: 0.2 | D3: =_xlfn.PERCENTILE.INC(Titanic[Familiares], B3) -> 0 | E3: SOLO | G3: =_xlfn.PERCENTILE.INC(Titanic[Pagado], B3) -> 105 | H3: PAGO BÁSICO
B4: 0.4 | D4: =_xlfn.PERCENTILE.INC(Titanic[Familiares], B4) -> 0 | G4: =_xlfn.PERCENTILE.INC(Titanic[Pagado], B4) -> 775 | H4: PAGO NORMAL
B5: 0.6 | D5: =_xlfn.PERCENTILE.INC(Titanic[Familiares], B5) -> 0 | G5: =_xlfn.PERCENTILE.INC(Titanic[Pagado], B5) -> 7925 | H5: PAGO LUJO
B6: 0.8 | D6: =_xlfn.PERCENTILE.INC(Titanic[Familiares], B6) -> 2 | E6: FAMILIA NORMAL | G6: =_xlfn.PERCENTILE.INC(Titanic[Pagado], B6) -> 86625 | H6: PAGO SÚPER LUJO
B7: 1 | D7: =_xlfn.PERCENTILE.INC(Titanic[Familiares], B7) -> 10 | E7: FAMILIA GRANDE | G7: =_xlfn.PERCENTILE.INC(Titanic[Pagado], B7) -> 5123292 | H7: MILLONARIO
D10: 0 | E10: SOLO
D11: 2 | E11: FAMILIA NORMAL
D12: 10 | E12: FAMILIA GRANDE

Sheet Hoja3
C2: EJE PERCENTIL
B4: {=Titanic[Edad Corrigida]} -> 22 | C4: =IFERROR(_xlfn.PERCENTRANK.INC(Titanic[Edad Corrigida], B4), "") -> 0.276 | E4: {=_xlfn._xlws.SORT(_xlfn.UNIQUE(Titanic[Edad Corrigida]))} -> 1 | F4: =IFERROR(ROUNDUP(E4/5, 0), "DESCONOCIDO") -> 1
B5: 38 | C5: =IFERROR(_xlfn.PERCENTRANK.INC(Titanic[Edad Corrigida], B5), "") -> 0.727 | E5: 2 | F5: =IFERROR(ROUNDUP(E5/5, 0), "DESCONOCIDO") -> 1
B6: 26 | C6: =IFERROR(_xlfn.PERCENTRANK.INC(Titanic[Edad Corrigida], B6), "") -> 0.412 | E6: 3 | F6: =IFERROR(ROUNDUP(E6/5, 0), "DESCONOCIDO") -> 1
B7: 35 | C7: =IFERROR(_xlfn.PERCENTRANK.INC(Titanic[Edad Corrigida], B7), "") -> 0.661 | E7: 4 | F7: =IFERROR(ROUNDUP(E7/5, 0), "DESCONOCIDO") -> 1
B8: 35 | C8: =IFERROR(_xlfn.PERCENTRANK.INC(Titanic[Edad Corrigida], B8), "") -> 0.661 | E8: 5 | F8: =IFERROR(ROUNDUP(E8/5, 0), "DESCONOCIDO") -> 1
C9: =IFERROR(_xlfn.PERCENTRANK.INC(Titanic[Edad Corrigida], B9), "") | E9: 6 | F9: =IFERROR(ROUNDUP(E9/5, 0), "DESCONOCIDO") -> 2
B10: 54 | C10: =IFERROR(_xlfn.PERCENTRANK.INC(Titanic[Edad Corrigida], B10), "") -> 0.922 | E10: 7 | F10: =IFERROR(ROUNDUP(E10/5, 0), "DESCONOCIDO") -> 2
B11: 2 | C11: =IFERROR(_xlfn.PERCENTRANK.INC(Titanic[Edad Corrigida], B11), "") -> 0.009 | E11: 8 | F11: =IFERROR(ROUNDUP(E11/5, 0), "DESCONOCIDO") -> 2
B12: 27 | C12: =IFERROR(_xlfn.PERCENTRANK.INC(Titanic[Edad Corrigida], B12), "") -> 0.437 | E12: 9 | F12: =IFERROR(ROUNDUP(E12/5, 0), "DESCONOCIDO") -> 2
B13: 14 | C13: =IFERROR(_xlfn.PERCENTRANK.INC(Titanic[Edad Corrigida], B13), "") -> 0.089 | E13: 10 | F13: =IFERROR(ROUNDUP(E13/5, 0), "DESCONOCIDO") -> 2
B14: 4 | C14: =IFERROR(_xlfn.PERCENTRANK.INC(Titanic[Edad Corrigida], B14), "") -> 0.032 | E14: 11 | F14: =IFERROR(ROUNDUP(E14/5, 0), "DESCONOCIDO") -> 3
B15: 58 | C15: =IFERROR(_xlfn.PERCENTRANK.INC(Titanic[Edad Corrigida], B15), "") -> 0.946 | E15: 12 | F15: =IFERROR(ROUNDUP(E15/5, 0), "DESCONOCIDO") -> 3
B16: 20 | C16: =IFERROR(_xlfn.PERCENTRANK.INC(Titanic[Edad Corrigida], B16), "") -> 0.22 | E16: 13 | F16: =IFERROR(ROUNDUP(E16/5, 0), "DESCONOCIDO") -> 3
B17: 39 | C17: =IFERROR(_xlfn.PERCENTRANK.INC(Titanic[Edad Corrigida], B17), "") -> 0.743 | E17: 14 | F17: =IFERROR(ROUNDUP(E17/5, 0), "DESCONOCIDO") -> 3
B18: 14 | C18: =IFERROR(_xlfn.PERCENTRANK.INC(Titanic[Edad Corrigida], B18), "") -> 0.089 | E18: 14.5 | F18: =IFERROR(ROUNDUP(E18/5, 0), "DESCONOCIDO") -> 3
B19: 55 | C19: =IFERROR(_xlfn.PERCENTRANK.INC(Titanic[Edad Corrigida], B19), "") -> 0.934 | E19: 15 | F19: =IFERROR(ROUNDUP(E19/5, 0), "DESCONOCIDO") -> 3
B20: 2 | C20: =IFERROR(_xlfn.PERCENTRANK.INC(Titanic[Edad Corrigida], B20), "") -> 0.009 | E20: 16 | F20: =IFERROR(ROUNDUP(E20/5, 0), "DESCONOCIDO") -> 4
C21: =IFERROR(_xlfn.PERCENTRANK.INC(Titanic[Edad Corrigida], B21), "") | E21: 17 | F21: =IFERROR(ROUNDUP(E21/5, 0), "DESCONOCIDO") -> 4
B22: 31 | C22: =IFERROR(_xlfn.PERCENTRANK.INC(Titanic[Edad Corrigida], B22), "") -> 0.566 | E22: 18 | F22: =IFERROR(ROUNDUP(E22/5, 0), "DESCONOCIDO") -> 4
C23: =IFERROR(_xlfn.PERCENTRANK.INC(Titanic[Edad Corrigida], B23), "") | E23: 19 | F23: =IFERROR(ROUNDUP(E23/5, 0), "DESCONOCIDO") -> 4
B24: 35 | C24: =IFERROR(_xlfn.PERCENTRANK.INC(Titanic[Edad Corrigida], B24), "") -> 0.661 | E24: 20 | F24: =IFERROR(ROUNDUP(E24/5, 0), "DESCONOCIDO") -> 4
B25: 34 | C25: =IFERROR(_xlfn.PERCENTRANK.INC(Titanic[Edad Corrigida], B25), "") -> 0.639 | E25: 20.5 | F25: =IFERROR(ROUNDUP(E25/5, 0), "DESCONOCIDO") -> 5
B26: 15 | C26: =IFERROR(_xlfn.PERCENTRANK.INC(Titanic[Edad Corrigida], B26), "") -> 0.099 | E26: 21 | F26: =IFERROR(ROUNDUP(E26/5, 0), "DESCONOCIDO") -> 5
B27: 28 | C27: =IFERROR(_xlfn.PERCENTRANK.INC(Titanic[Edad Corrigida], B27), "") -> 0.462 | E27: 22 | F27: =IFERROR(ROUNDUP(E27/5, 0), "DESCONOCIDO") -> 5
B28: 8 | C28: =IFERROR(_xlfn.PERCENTRANK.INC(Titanic[Edad Corrigida], B28), "") -> 0.06 | E28: 23 | F28: =IFERROR(ROUNDUP(E28/5, 0), "DESCONOCIDO") -> 5
B29: 38 | C29: =IFERROR(_xlfn.PERCENTRANK.INC(Titanic[Edad Corrigida], B29), "") -> 0.727 | E29: 23.5 | F29: =IFERROR(ROUNDUP(E29/5, 0), "DESCONOCIDO") -> 5
C30: =IFERROR(_xlfn.PERCENTRANK.INC(Titanic[Edad Corrigida], B30), "") | E30: 24 | F30: =IFERROR(ROUNDUP(E30/5, 0), "DESCONOCIDO") -> 5
B31: 19 | C31: =IFERROR(_xlfn.PERCENTRANK.INC(Titanic[Edad Corrigida], B31), "") -> 0.185 | E31: 24.5 | F31: =IFERROR(ROUNDUP(E31/5, 0), "DESCONOCIDO") -> 5
C32: =IFERROR(_xlfn.PERCENTRANK.INC(Titanic[Edad Corrigida], B32), "") | E32: 25 | F32: =IFERROR(ROUNDUP(E32/5, 0), "DESCONOCIDO") -> 5
C33: =IFERROR(_xlfn.PERCENTRANK.INC(Titanic[Edad Corrigida], B33), "") | E33: 26 | F33: =IFERROR(ROUNDUP(E33/5, 0), "DESCONOCIDO") -> 6
B34: 40 | C34: =IFERROR(_xlfn.PERCENTRANK.INC(Titanic[Edad Corrigida], B34), "") -> 0.762 | E34: 27 | F34: =IFERROR(ROUNDUP(E34/5, 0), "DESCONOCIDO") -> 6
C35: =IFERROR(_xlfn.PERCENTRANK.INC(Titanic[Edad Corrigida], B35), "") | E35: 28 | F35: =IFERROR(ROUNDUP(E35/5, 0), "DESCONOCIDO") -> 6
C36: =IFERROR(_xlfn.PERCENTRANK.INC(Titanic[Edad Corrigida], B36), "") | E36: 28.5 | F36: =IFERROR(ROUNDUP(E36/5, 0), "DESCONOCIDO") -> 6
B37: 66 | C37: =IFERROR(_xlfn.PERCENTRANK.INC(Titanic[Edad Corrigida], B37), "") -> 0.981 | E37: 29 | F37: =IFERROR(ROUNDUP(E37/5, 0), "DESCONOCIDO") -> 6
B38: 28 | C38: =IFERROR(_xlfn.PERCENTRANK.INC(Titanic[Edad Corrigida], B38), "") -> 0.462 | E38: 30 | F38: =IFERROR(ROUNDUP(E38/5, 0), "DESCONOCIDO") -> 6
B39: 42 | C39: =IFERROR(_xlfn.PERCENTRANK.INC(Titanic[Edad Corrigida], B39), "") -> 0.792 | E39: 30.5 | F39: =IFERROR(ROUNDUP(E39/5, 0), "DESCONOCIDO") -> 7
C40: =IFERROR(_xlfn.PERCENTRANK.INC(Titanic[Edad Corrigida], B40), "") | E40: 31 | F40: =IFERROR(ROUNDUP(E40/5, 0), "DESCONOCIDO") -> 7
B41: 21 | C41: =IFERROR(_xlfn.PERCENTRANK.INC(Titanic[Edad Corrigida], B41), "") -> 0.242 | E41: 32 | F41: =IFERROR(ROUNDUP(E41/5, 0), "DESCONOCIDO") -> 7
B42: 18 | C42: =IFERROR(_xlfn.PERCENTRANK.INC(Titanic[Edad Corrigida], B42), "") -> 0.148 | E42: 32.5 | F42: =IFERROR(ROUNDUP(E42/5, 0), "DESCONOCIDO") -> 7
B43: 14 | C43: =IFERROR(_xlfn.PERCENTRANK.INC(Titanic[Edad Corrigida], B43), "") -> 0.089 | E43: 33 | F43: =IFERROR(ROUNDUP(E43/5, 0), "DESCONOCIDO") -> 7
B44: 40 | C44: =IFERROR(_xlfn.PERCENTRANK.INC(Titanic[Edad Corrigida], B44), "") -> 0.762 | E44: 34 | F44: =IFERROR(ROUNDUP(E44/5, 0), "DESCONOCIDO") -> 7
B45: 27 | C45: =IFERROR(_xlfn.PERCENTRANK.INC(Titanic[Edad Corrigida], B45), "") -> 0.437 | E45: 34.5 | F45: =IFERROR(ROUNDUP(E45/5, 0), "DESCONOCIDO") -> 7
C46: =IFERROR(_xlfn.PERCENTRANK.INC(Titanic[Edad Corrigida], B46), "") | E46: 35 | F46: =IFERROR(ROUNDUP(E46/5, 0), "DESCONOCIDO") -> 7
B47: 3 | C47: =IFERROR(_xlfn.PERCENTRANK.INC(Titanic[Edad Corrigida], B47), "") -> 0.023 | E47: 36 | F47: =IFERROR(ROUNDUP(E47/5, 0), "DESCONOCIDO") -> 8
B48: 19 | C48: =IFERROR(_xlfn.PERCENTRANK.INC(Titanic[Edad Corrigida], B48), "") -> 0.185 | E48: 36.5 | F48: =IFERROR(ROUNDUP(E48/5, 0), "DESCONOCIDO") -> 8
C49: =IFERROR(_xlfn.PERCENTRANK.INC(Titanic[Edad Corrigida], B49), "") | E49: 37 | F49: =IFERROR(ROUNDUP(E49/5, 0), "DESCONOCIDO") -> 8
C50: =IFERROR(_xlfn.PERCENTRANK.INC(Titanic[Edad Corrigida], B50), "") | E50: 38 | F50: =IFERROR(ROUNDUP(E50/5, 0), "DESCONOCIDO") -> 8
C51: =IFERROR(_xlfn.PERCENTRANK.INC(Titanic[Edad Corrigida], B51), "") | E51: 39 | F51: =IFERROR(ROUNDUP(E51/5, 0), "DESCONOCIDO") -> 8
C52: =IFERROR(_xlfn.PERCENTRANK.INC(Titanic[Edad Corrigida], B52), "") | E52: 40 | F52: =IFERROR(ROUNDUP(E52/5, 0), "DESCONOCIDO") -> 8
B53: 18 | C53: =IFERROR(_xlfn.PERCENTRANK.INC(Titanic[Edad Corrigida], B53), "") -> 0.148 | E53: 40.5 | F53: =IFERROR(ROUNDUP(E53/5, 0), "DESCONOCIDO") -> 9
B54: 7 | C54: =IFERROR(_xlfn.PERCENTRANK.INC(Titanic[Edad Corrigida], B54), "") -> 0.056 | E54: 41 | F54: =IFERROR(ROUNDUP(E54/5, 0), "DESCONOCIDO") -> 9
B55: 21 | C55: =IFERROR(_xlfn.PERCENTRANK.INC(Titanic[Edad Corrigida], B55), "") -> 0.242 | E55: 42 | F55: =IFERROR(ROUNDUP(E55/5, 0), "DESCONOCIDO") -> 9
B56: 49 | C56: =IFERROR(_xlfn.PERCENTRANK.INC(Titanic[Edad Corrigida], B56), "") -> 0.88 | E56: 43 | F56: =IFERROR(ROUNDUP(E56/5, 0), "DESCONOCIDO") -> 9
B57: 29 | C57: =IFERROR(_xlfn.PERCENTRANK.INC(Titanic[Edad Corrigida], B57), "") -> 0.5 | E57: 44 | F57: =IFERROR(ROUNDUP(E57/5, 0), "DESCONOCIDO") -> 9
B58: 65 | C58: =IFERROR(_xlfn.PERCENTRANK.INC(Titanic[Edad Corrigida], B58), "") -> 0.977 | E58: 45 | F58: =IFERROR(ROUNDUP(E58/5, 0), "DESCONOCIDO") -> 9
C59: =IFERROR(_xlfn.PERCENTRANK.INC(Titanic[Edad Corrigida], B59), "") | E59: 45.5 | F59: =IFERROR(ROUNDUP(E59/5, 0), "DESCONOCIDO") -> 10
B60: 21 | C60: =IFERROR(_xlfn.PERCENTRANK.INC(Titanic[Edad Corrigida], B60), "") -> 0.242 | E60: 46 | F60: =IFERROR(ROUNDUP(E60/5, 0), "DESCONOCIDO") -> 10
B61: 28.5 | C61: =IFERROR(_xlfn.PERCENTRANK.INC(Titanic[Edad Corrigida], B61), "") -> 0.497 | E61: 47 | F61: =IFERROR(ROUNDUP(E61/5, 0), "DESCONOCIDO") -> 10
B62: 5 | C62: =IFERROR(_xlfn.PERCENTRANK.INC(Titanic[Edad Corrigida], B62), "") -> 0.046 | E62: 48 | F62: =IFERROR(ROUNDUP(E62/5, 0), "DESCONOCIDO") -> 10
B63: 11 | C63: =IFERROR(_xlfn.PERCENTRANK.INC(Titanic[Edad Corrigida], B63), "") -> 0.079 | E63: 49 | F63: =IFERROR(ROUNDUP(E63/5, 0), "DESCONOCIDO") -> 10
B64: 22 | C64: =IFERROR(_xlfn.PERCENTRANK.INC(Titanic[Edad Corrigida], B64), "") -> 0.276 | E64: 50 | F64: =IFERROR(ROUNDUP(E64/5, 0), "DESCONOCIDO") -> 10
B65: 38 | C65: =IFERROR(_xlfn.PERCENTRANK.INC(Titanic[Edad Corrigida], B65), "") -> 0.727 | E65: 51 | F65: =IFERROR(ROUNDUP(E65/5, 0), "DESCONOCIDO") -> 11
B66: 45 | C66: =IFERROR(_xlfn.PERCENTRANK.INC(Titanic[Edad Corrigida], B66), "") -> 0.831 | E66: 52 | F66: =IFERROR(ROUNDUP(E66/5, 0), "DESCONOCIDO") -> 11
B67: 4 | C67: =IFERROR(_xlfn.PERCENTRANK.INC(Titanic[Edad Corrigida], B67), "") -> 0.032 | E67: 53 | F67: =IFERROR(ROUNDUP(E67/5, 0), "DESCONOCIDO") -> 11
C68: =IFERROR(_xlfn.PERCENTRANK.INC(Titanic[Edad Corrigida], B68), "") | E68: 54 | F68: =IFERROR(ROUNDUP(E68/5, 0), "DESCONOCIDO") -> 11
C69: =IFERROR(_xlfn.PERCENTRANK.INC(Titanic[Edad Corrigida], B69), "") | E69: 55 | F69: =IFERROR(ROUNDUP(E69/5, 0), "DESCONOCIDO") -> 11
B70: 29 | C70: =IFERROR(_xlfn.PERCENTRANK.INC(Titanic[Edad Corrigida], B70), "") -> 0.5 | E70: 55.5 | F70: =IFERROR(ROUNDUP(E70/5, 0), "DESCONOCIDO") -> 12
B71: 19 | C71: =IFERROR(_xlfn.PERCENTRANK.INC(Titanic[Edad Corrigida], B71), "") -> 0.185 | E71: 56 | F71: =IFERROR(ROUNDUP(E71/5, 0), "DESCONOCIDO") -> 12
B72: 17 | C72: =IFERROR(_xlfn.PERCENTRANK.INC(Titanic[Edad Corrigida], B72), "") -> 0.13 | E72: 57 | F72: =IFERROR(ROUNDUP(E72/5, 0), "DESCONOCIDO") -> 12
B73: 26 | C73: =IFERROR(_xlfn.PERCENTRANK.INC(Titanic[Edad Corrigida], B73), "") -> 0.412 | E73: 58 | F73: =IFERROR(ROUNDUP(E73/5, 0), "DESCONOCIDO") -> 12
B74: 32 | C74: =IFERROR(_xlfn.PERCENTRANK.INC(Titanic[Edad Corrigida], B74), "") -> 0.59 | E74: 59 | F74: =IFERROR(ROUNDUP(E74/5, 0), "DESCONOCIDO") -> 12
B75: 16 | C75: =IFERROR(_xlfn.PERCENTRANK.INC(Titanic[Edad Corrigida], B75), "") -> 0.106 | E75: 60 | F75: =IFERROR(ROUNDUP(E75/5, 0), "DESCONOCIDO") -> 12
B76: 21 | C76: =IFERROR(_xlfn.PERCENTRANK.INC(Titanic[Edad Corrigida], B76), "") -> 0.242 | E76: 61 | F76: =IFERROR(ROUNDUP(E76/5, 0), "DESCONOCIDO") -> 13
B77: 26 | C77: =IFERROR(_xlfn.PERCENTRANK.INC(Titanic[Edad Corrigida], B77), "") -> 0.412 | E77: 62 | F77: =IFERROR(ROUNDUP(E77/5, 0), "DESCONOCIDO") -> 13
B78: 32 | C78: =IFERROR(_xlfn.PERCENTRANK.INC(Titanic[Edad Corrigida], B78), "") -> 0.59 | E78: 63 | F78: =IFERROR(ROUNDUP(E78/5, 0), "DESCONOCIDO") -> 13
B79: 25 | C79: =IFERROR(_xlfn.PERCENTRANK.INC(Titanic[Edad Corrigida], B79), "") -> 0.38 | E79: 64 | F79: =IFERROR(ROUNDUP(E79/5, 0), "DESCONOCIDO") -> 13
C80: =IFERROR(_xlfn.PERCENTRANK.INC(Titanic[Edad Corrigida], B80), "") | E80: 65 | F80: =IFERROR(ROUNDUP(E80/5, 0), "DESCONOCIDO") -> 13
C81: =IFERROR(_xlfn.PERCENTRANK.INC(Titanic[Edad Corrigida], B81), "") | E81: 66 | F81: =IFERROR(ROUNDUP(E81/5, 0), "DESCONOCIDO") -> 14
B82: 83 | C82: =IFERROR(_xlfn.PERCENTRANK.INC(Titanic[Edad Corrigida], B82), "") -> 0.997 | E82: 67 | F82: =IFERROR(ROUNDUP(E82/5, 0), "DESCONOCIDO") -> 14
B83: 30 | C83: =IFERROR(_xlfn.PERCENTRANK.INC(Titanic[Edad Corrigida], B83), "") -> 0.528 | E83: 70 | F83: =IFERROR(ROUNDUP(E83/5, 0), "DESCONOCIDO") -> 14
B84: 22 | C84: =IFERROR(_xlfn.PERCENTRANK.INC(Titanic[Edad Corrigida], B84), "") -> 0.276 | E84: 70.5 | F84: =IFERROR(ROUNDUP(E84/5, 0), "DESCONOCIDO") -> 15
B85: 29 | C85: =IFERROR(_xlfn.PERCENTRANK.INC(Titanic[Edad Corrigida], B85), "") -> 0.5 | E85: 71 | F85: =IFERROR(ROUNDUP(E85/5, 0), "DESCONOCIDO") -> 15
C86: =IFERROR(_xlfn.PERCENTRANK.INC(Titanic[Edad Corrigida], B86), "") | E86: 74 | F86: =IFERROR(ROUNDUP(E86/5, 0), "DESCONOCIDO") -> 15
B87: 28 | C87: =IFERROR(_xlfn.PERCENTRANK.INC(Titanic[Edad Corrigida], B87), "") -> 0.462 | E87: 75 | F87: =IFERROR(ROUNDUP(E87/5, 0), "DESCONOCIDO") -> 15
B88: 17 | C88: =IFERROR(_xlfn.PERCENTRANK.INC(Titanic[Edad Corrigida], B88), "") -> 0.13 | E88: 80 | F88: =IFERROR(ROUNDUP(E88/5, 0), "DESCONOCIDO") -> 16
B89: 33 | C89: =IFERROR(_xlfn.PERCENTRANK.INC(Titanic[Edad Corrigida], B89), "") -> 0.618 | E89: 83 | F89: =IFERROR(ROUNDUP(E89/5, 0), "DESCONOCIDO") -> 17
B90: 16 | C90: =IFERROR(_xlfn.PERCENTRANK.INC(Titanic[Edad Corrigida], B90), "") -> 0.106 | E90: 92 | F90: =IFERROR(ROUNDUP(E90/5, 0), "DESCONOCIDO") -> 19
C91: =IFERROR(_xlfn.PERCENTRANK.INC(Titanic[Edad Corrigida], B91), "") | F91: =IFERROR(ROUNDUP(E91/5, 0), "DESCONOCIDO") -> DESCONOCIDO
B92: 23 | C92: =IFERROR(_xlfn.PERCENTRANK.INC(Titanic[Edad Corrigida], B92), "") -> 0.314
B93: 24 | C93: =IFERROR(_xlfn.PERCENTRANK.INC(Titanic[Edad Corrigida], B93), "") -> 0.336
B94: 29 | C94: =IFERROR(_xlfn.PERCENTRANK.INC(Titanic[Edad Corrigida], B94), "") -> 0.5
B95: 20 | C95: =IFERROR(_xlfn.PERCENTRANK.INC(Titanic[Edad Corrigida], B95), "") -> 0.22
B96: 46 | C96: =IFERROR(_xlfn.PERCENTRANK.INC(Titanic[Edad Corrigida], B96), "") -> 0.851
B97: 26 | C97: =IFERROR(_xlfn.PERCENTRANK.INC(Titanic[Edad Corrigida], B97), "") -> 0.412
B98: 59 | C98: =IFERROR(_xlfn.PERCENTRANK.INC(Titanic[Edad Corrigida], B98), "") -> 0.953
C99: =IFERROR(_xlfn.PERCENTRANK.INC(Titanic[Edad Corrigida], B99), "")
B100: 71 | C100: =IFERROR(_xlfn.PERCENTRANK.INC(Titanic[Edad Corrigida], B100), "") -> 0.988
B101: 23 | C101: =IFERROR(_xlfn.PERCENTRANK.INC(Titanic[Edad Corrigida], B101), "") -> 0.314
B102: 34 | C102: =IFERROR(_xlfn.PERCENTRANK.INC(Titanic[Edad Corrigida], B102), "") -> 0.639
...

Sheet Práctica 1
E6: PERCENTIL
C7: I | D7: X | E7: A
C8: 6
C9: 18
C10: 20
C11: 27
C12: 29
C13: 30
C14: 32
C15: 33
C16: 37
C17: 43
C18: 46
C19: 47
... C184: 889
C185: 165 | D185: 1 | E185: 0
C186: 173 | D186: 1 | E186: 0
C187: 184 | D187: 1 | E187: 0
C188: 382 | D188: 1 | E188: 0
C189: 387 | D189: 1 | E189: 0
C190: 789 | D190: 1 | E190: 0
C191: 828 | D191: 1 | E191: 0 | H191: =COUNTA(D185:D191) -> 7 | I191: 891 | J191: =H191/I191 -> 0.0078563412
C192: 8 | D192: 2 | E192: 0.009
C193: 17 | D193: 2 | E193: 0.009
C194: 120 | D194: 2 | E194: 0.009
C195: 206 | D195: 2 | E195: 0.009
C196: 298 | D196: 2 | E196: 0.009
C197: 341 | D197: 2 | E197: 0.009
C198: 480 | D198: 2 | E198: 0.009
C199: 531 | D199: 2 | E199: 0.009 | L199: {=COUNT(_xlfn._xlws.FILTER(Titanic[Edad Corrigida], Titanic[Edad Corrigida] = L200))} -> 7 | M199: {=COUNT(_xlfn._xlws.FILTER(Titanic[Edad Corrigida], Titanic[Edad Corrigida] = M200))} -> 10 | N199: {=COUNT(_xlfn._xlws.FILTER(Titanic[Edad Corrigida], Titanic[Edad Corrigida] = N200))} -> 6 | O199: {=COUNT(_xlfn._xlws.FILTER(Titanic[Edad Corrigida], Titanic[Edad Corrigida] = O200))} -> 10 | P199: {=COUNT(_xlfn._xlws.FILTER(Titanic[Edad Corrigida], Titanic[Edad Corrigida] = P200))} -> 4
C200: 643 | D200: 2 | E200: 0.009 | L200: {=TRANSPOSE(_xlfn._xlws.SORT(_xlfn.UNIQUE(Titanic[Edad Corrigida])))} -> 1 | M200: 2 | N200: 3 | O200: 4 | P200: 5 | Q200: 6 | R200: 7 | S200: 8 | T200: 9 | U200: 10 | V200: 11 | W200: 12 | X200: 13 | Y200: 14 | Z200: 14.5 | AA200: 15 | AB200: 16 | AC200: 17 | AD200: 18 | AE200: 19 | AF200: 20 | AG200: 20.5 | AH200: 21 | AI200: 22 | AJ200: 23 | AK200: 23.5 | AL200: 24 | AM200: 24.5 | AN200: 25 | AO200: 26 | AP200: 27 | AQ200: 28 | AR200: 28.5 | AS200: 29 | AT200: 30 | AU200: 30.5 | AV200: 31 | AW200: 32 | AX200: 32.5 | AY200: 33 | AZ200: 34 | BA200: 34.5 | BB200: 35 | BC200: 36 | BD200: 36.5 | BE200: 37 | BF200: 38 | BG200: 39 | BH200: 40 | BI200: 40.5 | BJ200: 41 | BK200: 42 | BL200: 43 | BM200: 44 | BN200: 45 | BO200: 45.5 | BP200: 46 | BQ200: 47 | BR200: 48 | BS200: 49 | BT200: 50 | BU200: 51 | BV200: 52 | BW200: 53 | BX200: 54 | BY200: 55 | BZ200: 55.5 | CA200: 56 | CB200: 57 | CC200: 58 | CD200: 59 | CE200: 60 | CF200: 61 | CG200: 62 | CH200: 63 | CI200: 64 | CJ200: 65 | CK200: 66 | CL200: 67 | CM200: 70 | CN200: 70.5 | CO200: 71 | CP200: 74 | CQ200: 75 | CR200: 80 | CS200: 83 | CT200: 92
C201: 825 | D201: 2 | E201: 0.009 | H201: =COUNT(D192:D201) -> 10 | I201: 891 | J201: =H201/I201 -> 0.011223345
C202: 44 | D202: 3 | E202: 0.023 | L202: {=_xlfn._xlws.FILTER(Titanic[Edad Corrigida], Titanic[Edad Corrigida] = L200)} -> 1 | M202: {=_xlfn._xlws.FILTER(Titanic[Edad Corrigida], Titanic[Edad Corrigida] = M200)} -> 2 | N202: {=_xlfn._xlws.FILTER(Titanic[Edad Corrigida], Titanic[Edad Corrigida] = N200)} -> 3 | O202: {=_xlfn._xlws.FILTER(Titanic[Edad Corrigida], Titanic[Edad Corrigida] = O200)} -> 4 | P202: {=_xlfn._xlws.FILTER(Titanic[Edad Corrigida], Titanic[Edad Corrigida] = P200)} -> 5
C203: 194 | D203: 3 | E203: 0.023 | L203: 1 | M203: 2 | N203: 3 | O203: 4 | P203: 5
C204: 262 | D204: 3 | E204: 0.023 | L204: 1 | M204: 2 | N204: 3 | O204: 4 | P204: 5
C205: 349 | D205: 3 | E205: 0.023 | L205: 1 | M205: 2 | N205: 3 | O205: 4 | P205: 5
C206: 375 | D206: 3 | E206: 0.023 | L206: 1 | M206: 2 | N206: 3 | O206: 4
C207: 408 | D207: 3 | E207: 0.023 | H207: =COUNT(D202:D207) -> 6 | I207: 891 | J207: =H207/I207 -> 0.0067340067 | L207: 1 | M207: 2 | N207: 3 | O207: 4
C208: 11 | D208: 4 | E208: 0.032 | L208: 1 | M208: 2 | O208: 4
C209: 64 | D209: 4 | E209: 0.032 | M209: 2 | O209: 4
C210: 172 | D210: 4 | E210: 0.032 | M210: 2 | O210: 4
C211: 185 | D211: 4 | E211: 0.032 | M211: 2 | O211: 4
C212: 446 | D212: 4 | E212: 0.032
C213: 619 | D213: 4 | E213: 0.032
C214: 692 | D214: 4 | E214: 0.032
C215: 751 | D215: 4 | E215: 0.032
C216: 851 | D216: 4 | E216: 0.032
C217: 870 | D217: 4 | E217: 0.032
C218: 59 | D218: 5 | E218: 0.046
C219: 234 | D219: 5 | E219: 0.046
C220: 449 | D220: 5 | E220: 0.046
C221: 778 | D221: 5 | E221: 0.046
C222: 721 | D222: 6 | E222: 0.051
C223: 752 | D223: 6 | E223: 0.051
... C227: 536 | D227: 7 | E227: 0.056
C228: 25 | D228: 8 | E228: 0.06 | F228: GRUPOS AUTOMÁTICOS
C229: 238 | D229: 8 | E229: 0.06 | F229: (Grupos uniformes)
C230: 550 | D230: 8 | E230: 0.06 | K230: CORTE DECIL | O230: DECILES 10%
C231: 788 | D231: 8 | E231: 0.06 | G231: DECIL 1 | H231: 0.1 | I231: 0% - 10% | J231: 15 | K231: =_xlfn.PERCENTILE.INC(Titanic[Edad Corrigida],H231) -> 15 | L231: 1. INFANTE | M231: {=COUNT(_xlfn._xlws.FILTER(Titanic[Indice], (Titanic[Edad Corrigida] >= 0)*(Titanic[Edad Corrigida]<=K231))) / 891} -> 0.085297419 | O231: QUINTILES 20%
C232: 148 | D232: 9 | E232: 0.065 | G232: DECIL 2 | H232: 0.2 | I232: 11%-20% | J232: 19.5 | K232: =_xlfn.PERCENTILE.INC(Titanic[Edad Corrigida],H232) -> 19 | L232: 2. ADOLESCENTE | M232: {=COUNT(_xlfn._xlws.FILTER(Titanic[Indice], (Titanic[Edad Corrigida]<=K232))) / 891} -> 0.17620651 | O232: CUARTILES 25%
C233: 166 | D233: 9 | E233: 0.065 | G233: DECIL 3 | H233: 0.3 | I233: 21%-30% | J233: 22.5 | K233: =_xlfn.PERCENTILE.INC(Titanic[Edad Corrigida],H233) -> 22 | L233: 3. JOVEN | M233: {=COUNT(_xlfn._xlws.FILTER(Titanic[Indice], (Titanic[Edad Corrigida]<=K233))) / 891} -> 0.25140292
C234: 183 | D234: 9 | E234: 0.065 | G234: DECIL 4 | H234: 0.4 | I234: 31%-40% | J234: 25.5 | K234: =_xlfn.PERCENTILE.INC(Titanic[Edad Corrigida],H234) -> 25 | L234: 4. ADULTO JOVEN | M234: {=COUNT(_xlfn._xlws.FILTER(Titanic[Indice], (Titanic[Edad Corrigida]<=K234))) / 891} -> 0.32996633
C235: 481 | D235: 9 | E235: 0.065 | G235: DECIL 5 | H235: 0.5 | I235: 41%-50% | J235: 29 | K235: =_xlfn.PERCENTILE.INC(Titanic[Edad Corrigida],H235) -> 28.75 | L235: 5. ADULTO | M235: {=COUNT(_xlfn._xlws.FILTER(Titanic[Indice], (Titanic[Edad Corrigida]<=K235))) / 891} -> 0.4006734
C236: 490 | D236: 9 | E236: 0.065 | G236: DECIL 6 | H236: 0.6 | I236: 51%-60% | J236: 32.5 | K236: =_xlfn.PERCENTILE.INC(Titanic[Edad Corrigida],H236) -> 32 | L236: 6. ADULTO 1 | M236: {=COUNT(_xlfn._xlws.FILTER(Titanic[Indice], (Titanic[Edad Corrigida]<=K236))) / 891} -> 0.49270483
C237: 542 | D237: 9 | E237: 0.065 | G237: DECIL 7 | H237: 0.7 | I237: 61%-70% | J237: 36.5 | K237: =_xlfn.PERCENTILE.INC(Titanic[Edad Corrigida],H237) -> 36 | L237: 7. ADULTO 2 | M237: {=COUNT(_xlfn._xlws.FILTER(Titanic[Indice], (Titanic[Edad Corrigida]<=K237))) / 891} -> 0.57463524
C238: 635 | D238: 9 | E238: 0.065 | G238: DECIL 8 | H238: 0.8 | I238: 71%-80% | J238: 42.5 | K238: =_xlfn.PERCENTILE.INC(Titanic[Edad Corrigida],H238) -> 42 | L238: 8. ADULTO 3 | M238: {=COUNT(_xlfn._xlws.FILTER(Titanic[Indice], (Titanic[Edad Corrigida]<=K238))) / 891} -> 0.64983165
C239: 853 | D239: 9 | E239: 0.065 | G239: DECIL 9 | H239: 0.9 | I239: 81%-90% | J239: 51 | K239: =_xlfn.PERCENTILE.INC(Titanic[Edad Corrigida],H239) -> 50 | L239: 9. ADULTO 4 | M239: {=COUNT(_xlfn._xlws.FILTER(Titanic[Indice], (Titanic[Edad Corrigida]<=K239))) / 891} -> 0.72278339
C240: 420 | D240: 10 | E240: 0.077 | G240: DECIL 10 | H240: 1 | I240: 91%-100% | J240: 92 | K240: =_xlfn.PERCENTILE.INC(Titanic[Edad Corrigida],H240) -> 92 | L240: A. ADULTO MAYOR | M240: {=COUNT(_xlfn._xlws.FILTER(Titanic[Indice], (Titanic[Edad Corrigida]<=K240))) / 891} -> 0.8013468
C241: 820 | D241: 10 | E241: 0.077
C242: 60 | D242: 11 | E242: 0.079 | K242: CORTE QUINTIL
C243: 543 | D243: 11 | E243: 0.079 | G243: QUINTIL 1 | H243: 0.2 | I243: 0-20% | K243: =_xlfn.PERCENTILE.INC(Titanic[Edad Corrigida], H243) -> 19
C244: 732 | D244: 11 | E244: 0.079 | G244: QUINTIL 2 | H244: 0.4 | I244: 21%-40% | K244: =_xlfn.PERCENTILE.INC(Titanic[Edad Corrigida], H244) -> 25
C245: 803 | D245: 11 | E245: 0.079 | G245: QUINTIL 3 | H245: 0.6 | I245: 41%-60% | K245: =_xlfn.PERCENTILE.INC(Titanic[Edad Corrigida], H245) -> 32
C246: 126 | D246: 12 | E246: 0.085 | G246: QUINTIL 4 | H246: 0.8 | I246: 61%-80% | K246: =_xlfn.PERCENTILE.INC(Titanic[Edad Corrigida], H246) -> 42
C247: 447 | D247: 13 | E247: 0.086 | G247: QUINTIL 5 | H247: 1 | I247: 81%-100% | K247: =_xlfn.PERCENTILE.INC(Titanic[Edad Corrigida], H247) -> 92
C248: 781 | D248: 13 | E248: 0.086
C249: 10 | D249: 14 | E249: 0.089 | H249: SI([@Edad]="", "", SI([@Edad]>=100, [@Edad] / 10, [@Edad])) | M249: 1. Corregir la edad
C250: 15 | D250: 14 | E250: 0.089
C251: 40 | D251: 14 | E251: 0.089 | H251: SI.ERROR(RANGO.PERCENTIL.INC(Titanic[Edad Corrigida], B4), "") | M251: (Opcional) Obtener todos los percentiles
C252: 436 | D252: 14 | E252: 0.089
C253: 684 | D253: 14 | E253: 0.089 | H253: PERCENTIL.INC(Titanic[Edad Corrigida], H243) | L253: 2. Obtener solo los percentiles de interés (deciles, quintiles, cuartiles) y tratarlos como cortes categóricos (grupos automáticos/uniformes)
C254: 687 | D254: 14 | E254: 0.089
C255: 112 | D255: 14.5 | E255: 0.098
C256: 23 | D256: 15 | E256: 0.099
C257: 353 | D257: 15 | E257: 0.099
C258: 690 | D258: 15 | E258: 0.099
C259: 831 | D259: 15 | E259: 0.099 | G259: Práctica 1: | M259: Entrega
C260: 876 | D260: 15 | E260: 0.099 | G260: Reclasifica las edades por grupos quintiles
C261: 72 | D261: 16 | E261: 0.106 | G261: Asigna una etiqueta humana a cada grupo quintil | M261: alan@belatrix.com
C262: 87 | D262: 16 | E262: 0.106 | G262: Crea una tabla dinámica para anlizar las edades quintiles contra la supervivencia y agrega un segmentador | M262: administracion@belatrix.com
C263: 139 | D263: 16 | E263: 0.106 | M263: laura.ramirezt@scotiabank.com.mx
C264: 157 | D264: 16 | E264: 0.106 | G264: Anoten un informe/reporte de lo que observan en la gráfica de barras apiladas al 100%, para determinar como cambia la supervivencia por edad y sexo (similar al Análisis de Edades por Deciles)
C265: 209 | D265: 16 | E265: 0.106
C266: 221 | D266: 16 | E266: 0.106
C267: 267 | D267: 16 | E267: 0.106 | G267: * Para el fin de semana
C268: 283 | D268: 16 | E268: 0.106
C269: 330 | D269: 16 | E269: 0.106
C270: 334 | D270: 16 | E270: 0.106
C271: 505 | D271: 16 | E271: 0.106
C272: 575 | D272: 16 | E272: 0.106
...

Sheet Hoja6
B2: EDAD
B3: {=Titanic[Edad Corrigida]} -> 22
B4: 38
B5: 26
B6: 35
B7: 35
B9: 54
B10: 2
B11: 27
B12: 14
B13: 4
B14: 58
B15: 20
B16: 39
... B893: 32

Sheet Hoja7
B5: 22 | D5: Posición | F5: Jerarquía | G5: Porcentaje
B6: 38 | D6: 245 | E6: 92 | F6: 1 | G6: 1
B7: 26 | D7: 61 | E7: 83 | F7: 2 | G7: 0.997
B8: 35 | D8: 666 | E8: 83 | F8: 2 | G8: 0.997
B9: 35 | D9: 500 | E9: 80 | F9: 4 | G9: 0.995
B10: 54 | D10: 376 | E10: 75 | F10: 5 | G10: 0.992
B11: 2 | D11: 511 | E11: 75 | F11: 5 | G11: 0.992
B12: 27 | D12: 681 | E12: 74 | F12: 7 | G12: 0.991
B13: 14 | D13: 76 | E13: 71 | F13: 8 | G13: 0.988
B14: 4 | D14: 395 | E14: 71 | F14: 8 | G14: 0.988
B15: 58 | D15: 93 | E15: 70.5 | F15: 10 | G15: 0.987
B16: 20 | D16: 533 | E16: 70 | F16: 11 | G16: 0.984
B17: 39 | D17: 594 | E17: 70 | F17: 11 | G17: 0.984
... B718: 32 | D718: 630 | E718: 1 | F718: 708 | G718: 0
D719: 663 | E719: 1 | F719: 708 | G719: 0
D720: 1 | F720: #N/A | G720: #N/A
D721: 716 | F721: #N/A | G721: #N/A
D722: 717 | F722: #N/A | G722: #N/A
D723: 718 | F723: #N/A | G723: #N/A
D724: 719 | F724: #N/A | G724: #N/A
D725: 720 | F725: #N/A | G725: #N/A
D726: 721 | F726: #N/A | G726: #N/A
D727: 722 | F727: #N/A | G727: #N/A
D728: 723 | F728: #N/A | G728: #N/A
D729: 724 | F729: #N/A | G729: #N/A
D730: 725 | F730: #N/A | G730: #N/A
D731: 726 | F731: #N/A | G731: #N/A
... D895: 890 | F895: #N/A | G895: #N/A
